{
  "last_updated": "2026-07-16T11:17:28.887936+00:00",
  "markets": [
    {
      "id": "0x0c4cd2055d6ea89354ffddc55d6dbcef9355748112ea952fc925f3db6a5c457f",
      "question": "Will Argentina win the 2026 FIFA World Cup?",
      "volume": "152332156.17439494",
      "liquidity": "6350322.09854",
      "end_date": "2026-07-20T00:00:00Z"
    },
    {
      "id": "0xb6d6f15a1b5d08753653f1867ccd6126badfbe182a75159a330dc7b15336b309",
      "question": "Will Gedion Timothewos be the next Prime Minister of Ethiopia?",
      "volume": "52188328.64351004",
      "liquidity": "23596.93322",
      "end_date": "2026-06-01T00:00:00Z"
    },
    {
      "id": "0x7976b8dbacf9077eb1453a62bcefd6ab2df199acd28aad276ff0d920d6992892",
      "question": "Will Spain win the 2026 FIFA World Cup?",
      "volume": "120974981.13162613",
      "liquidity": "6550291.28396",
      "end_date": "2026-07-20T00:00:00Z"
    },
    {
      "id": "0x8b5120790c8f89cfd7a6666fb413990f9ef740d2b0826b2690dbc5fd6788f5c4",
      "question": "LoL: Bilibili Gaming vs T1 (BO1) - Esports World Cup Group C",
      "volume": "4161146.1674879803",
      "liquidity": "888845.47658",
      "end_date": "2026-07-16T15:00:00Z"
    },
    {
      "id": "0xe7fa223cd125e6d068d1f5c4fe1aa6a35e395f90915f7b7d983027ca646dc891",
      "question": "LoL: G2 Esports vs AG.AL (BO1) - Esports World Cup Group A",
      "volume": "2576267.2908200156",
      "liquidity": "673618.22275",
      "end_date": "2026-07-16T16:10:00Z"
    },
    {
      "id": "0x091f1b8f82139c2003607f97ab88fd0f1fc8f75708935c619858e8e508622c46",
      "question": "LoL: Hanwha Life Esports vs JD Gaming (BO1) - Esports World Cup Group D",
      "volume": "2325900.9226010027",
      "liquidity": "725409.52184",
      "end_date": "2026-07-16T16:10:00Z"
    },
    {
      "id": "0x2a28cc33492516116690a20d290f9922acbe0ed367ff52a6082154474c7f2971",
      "question": "Will the Fed increase interest rates by 50+ bps after the July 2026 meeting?",
      "volume": "12638186.210165866",
      "liquidity": "746728.89728",
      "end_date": "2026-07-29T00:00:00Z"
    },
    {
      "id": "0xd2a8caba5559bc21e14f6b2aa504cb14a1782751658b71409e25b82e432c0a97",
      "question": "Will Lionel Messi be the top goalscorer at the 2026 FIFA World Cup?",
      "volume": "5201130.85480996",
      "liquidity": "501367.29424",
      "end_date": "2026-07-20T00:00:00Z"
    },
    {
      "id": "0x4266ab921148974f104cbadd099e13bca989441bf58acfd2a08fc6cc7440e1a1",
      "question": "Will Mohammad Khatami be head of state in Iran end of 2026?",
      "volume": "3587847.160268981",
      "liquidity": "50639.56782",
      "end_date": "2026-12-31T00:00:00Z"
    },
    {
      "id": "0x5db999fad322cea2914535aae5517060c3f80ad6d8c0231cde2124a434d16846",
      "question": "Will the U.S. invade Iran before 2027?",
      "volume": "43112102.36052015",
      "liquidity": "831355.1916",
      "end_date": "2026-12-31T00:00:00Z"
    },
    {
      "id": "0x8bf1c1536ecb1c08fe13c6b71e8ab1f58bf3461c4cb79f5f1679f869a06aef86",
      "question": "Will there be no change in Fed interest rates after the July 2026 meeting?",
      "volume": "19131495.873963084",
      "liquidity": "588287.88021",
      "end_date": "2026-07-29T00:00:00Z"
    },
    {
      "id": "0xca1d1139b0c3a29983407f499476ae642482788e841a277eb86faeeb9fa4a85c",
      "question": "Will John Fetterman win the 2028 Democratic presidential nomination?",
      "volume": "23970934.670644134",
      "liquidity": "1920057.95318",
      "end_date": "2028-11-07T00:00:00Z"
    },
    {
      "id": "0x3107a083adef4e45938a55f966e5bfeb5320a62c5ce67b2af65ce8db1c3dcddc",
      "question": "LoL: Sentinels vs Gen.G (BO1) - Esports World Cup Group B",
      "volume": "798393.5351600009",
      "liquidity": "380668.4446",
      "end_date": "2026-07-16T15:00:00Z"
    },
    {
      "id": "0xfa021d817ad33e0fa28e04051b4fea25b0a090e94bb1b2a38b377bce9778eb8e",
      "question": "Will Kylian Mbappe be the top goalscorer at the 2026 FIFA World Cup?",
      "volume": "5010926.956552907",
      "liquidity": "346618.5609",
      "end_date": "2026-07-20T00:00:00Z"
    },
    {
      "id": "0x53da62774d757d6a651c69a1aca70f7765ed6b840bd1f4b209692f8d6c0c2d4e",
      "question": "Exact Score: Spain 2 - 3 Argentina?",
      "volume": "779082.6182670001",
      "liquidity": "159118.59184",
      "end_date": "2026-07-19T19:00:00Z"
    },
    {
      "id": "0xeefef4320deec275a7191ad901469eec59544dc1fd53fed93f6d3b97c33787a5",
      "question": "Will Mikel Oyarzabal be the top goalscorer at the 2026 FIFA World Cup?",
      "volume": "5068815.086162995",
      "liquidity": "258265.71758",
      "end_date": "2026-07-20T00:00:00Z"
    },
    {
      "id": "0xb5c0abeecb5502e6e8d83155c27819174d8317af3c425c3afc5a8c45257a3793",
      "question": "Will the Fed increase interest rates by 25 bps after the July 2026 meeting?",
      "volume": "14058805.123449177",
      "liquidity": "687572.7586",
      "end_date": "2026-07-29T00:00:00Z"
    },
    {
      "id": "0x4ede078cae84a5877ac32d7fb48811e5c23549a1904b7df06ff7935c6d79d831",
      "question": "Will the Fed decrease interest rates by 25 bps after the July 2026 meeting?",
      "volume": "10238681.879763078",
      "liquidity": "658966.64034",
      "end_date": "2026-07-29T00:00:00Z"
    },
    {
      "id": "0x0e7c959150b4e768b1b474679509e7e5751f1cc2da09f9266b9c91a4af2911c7",
      "question": "Swiss Open: Juan Manuel Cerundolo vs Miomir Kecmanovic",
      "volume": "640304.324773001",
      "liquidity": "500536.80528",
      "end_date": "2026-07-22T08:00:00Z"
    },
    {
      "id": "0xe61d096d818b247ce0add9caacdbe34dee528471e555c200a98e46184d33a94e",
      "question": "Swedish Open: Nikoloz Basilashvili vs Thiago Agustin Tirante",
      "volume": "631196.5287699999",
      "liquidity": "207005.2229",
      "end_date": "2026-07-22T08:00:00Z"
    }
  ]
}