{
  "last_updated": "2026-07-21T12:52:59.844313+00:00",
  "markets": [
    {
      "id": "0xc0b7319f73f248310b059c231fb069e64dbd68ca81dd9933728ca192b54c3cc4",
      "question": "Will Trump be in the WC Champions Photo?",
      "volume": "8586797.91479103",
      "liquidity": "3185236.0902",
      "end_date": "2026-07-20T03:59:00Z"
    },
    {
      "id": "0xf5ee4b6bd7d585c0e12e530074d0324493c302b82e127c832d15c89a610c0453",
      "question": "Will Demeke Mekonnen be the next Prime Minister of Ethiopia?",
      "volume": "22723294.478799995",
      "liquidity": "14741.60844",
      "end_date": "2026-06-01T00:00:00Z"
    },
    {
      "id": "0xfd6176f8c9a59105f80e060a77c4099881c5f2d9e0ceab88e55cf978462fab7f",
      "question": "Will Gretchen Whitmer win the 2028 US Presidential Election?",
      "volume": "15232676.185634835",
      "liquidity": "264460.52522",
      "end_date": "2028-11-07T00:00:00Z"
    },
    {
      "id": "0x5810d53c38309da76701bafc48be28b2a0e17a4a34f5331b105572a87530026b",
      "question": "LoL: Gen.G vs T1 (BO1) - KeSPA Cup Group Stage",
      "volume": "1427878.6876279966",
      "liquidity": "150498.1263",
      "end_date": "2026-07-21T14:10:00Z"
    },
    {
      "id": "0x4ede078cae84a5877ac32d7fb48811e5c23549a1904b7df06ff7935c6d79d831",
      "question": "Will the Fed decrease interest rates by 25 bps after the July 2026 meeting?",
      "volume": "13425622.078999076",
      "liquidity": "588213.22174",
      "end_date": "2026-07-29T00:00:00Z"
    },
    {
      "id": "0xd88cbd1c16dc47cf4edb66df252b29056042c6abc9400c6e170b3604b5900f23",
      "question": "LoL: T1 vs Kiwoom DRX (BO1) - KeSPA Cup Group Stage",
      "volume": "937932.6293499981",
      "liquidity": "669935.86834",
      "end_date": "2026-07-21T17:35:00Z"
    },
    {
      "id": "0xf6ef7c5dc55dd13c111930a1a966dda70392dea8385d8f086a2e6392a59ade8e",
      "question": "Counter-Strike: M80 vs NIP (BO3) - BLAST Bounty Qualifier",
      "volume": "873393.4847970017",
      "liquidity": "263811.40215",
      "end_date": "2026-07-21T16:00:00Z"
    },
    {
      "id": "0xc09821181a9f98e38e77bae7e9b1e94f843b47bf1b3fd457c9f0283f19a8dfa9",
      "question": "LoL: Hanwha Life Esports vs Nongshim Red Force (BO1) - KeSPA Cup Group Stage",
      "volume": "790268.601202",
      "liquidity": "483981.69579",
      "end_date": "2026-07-21T16:35:00Z"
    },
    {
      "id": "0x3d675f1c88099a57c12abca632cf926be1bf430125168321de06234e9930fe1a",
      "question": "Will the Fed decrease interest rates by 50+ bps after the July 2026 meeting?",
      "volume": "11344739.700148918",
      "liquidity": "1955457.11044",
      "end_date": "2026-07-29T00:00:00Z"
    },
    {
      "id": "0x7465a6bf86dccb6e86ba714c0ca7a99c2f2e47d05bb9575d190333ec5cba1246",
      "question": "LoL: HANJIN BRION vs Gen.G (BO1) - KeSPA Cup Group Stage",
      "volume": "663801.2111919996",
      "liquidity": "223923.40069",
      "end_date": "2026-07-21T15:50:00Z"
    },
    {
      "id": "0xe39adea057926dc197fe30a441f57a340b2a232d5a687010f78bba9b6e02620f",
      "question": "Will Gretchen Whitmer win the 2028 Democratic presidential nomination?",
      "volume": "11816382.714380989",
      "liquidity": "183539.94928",
      "end_date": "2028-11-07T00:00:00Z"
    },
    {
      "id": "0x49cc6caec3004983fc70010e60f66cc3d575042c846da60fde5ad51bc26f749b",
      "question": "LoL: KT Rolster vs Dplus KIA (BO1) - KeSPA Cup Group Stage",
      "volume": "642098.6592260001",
      "liquidity": "299747.33276",
      "end_date": "2026-07-21T14:55:00Z"
    },
    {
      "id": "0x8bf1c1536ecb1c08fe13c6b71e8ab1f58bf3461c4cb79f5f1679f869a06aef86",
      "question": "Will there be no change in Fed interest rates after the July 2026 meeting?",
      "volume": "21732669.85628281",
      "liquidity": "703900.94829",
      "end_date": "2026-07-29T00:00:00Z"
    },
    {
      "id": "0xb5c0abeecb5502e6e8d83155c27819174d8317af3c425c3afc5a8c45257a3793",
      "question": "Will the Fed increase interest rates by 25 bps after the July 2026 meeting?",
      "volume": "16102939.379605476",
      "liquidity": "630900.01673",
      "end_date": "2026-07-29T00:00:00Z"
    },
    {
      "id": "0x5db999fad322cea2914535aae5517060c3f80ad6d8c0231cde2124a434d16846",
      "question": "Will the U.S. invade Iran before 2027?",
      "volume": "45871876.04262392",
      "liquidity": "621536.3417",
      "end_date": "2026-12-31T00:00:00Z"
    },
    {
      "id": "0xa542045d965c3db3d8d065468640f7e020d7716420d7ba2af89d6793782aac44",
      "question": "Will Ulsan HD FC win on 2026-07-21?",
      "volume": "422782.88157000084",
      "liquidity": "158840.84941",
      "end_date": "2026-07-21T10:30:00Z"
    },
    {
      "id": "0xcdc8bc65cbd4db9dd24c0b05de9e86b14232beb8e8d7e26326c2ac80278a5dc4",
      "question": "Will Jeonbuk Hyundai Motors FC win on 2026-07-21?",
      "volume": "415803.5889589992",
      "liquidity": "118228.10615",
      "end_date": "2026-07-21T10:30:00Z"
    },
    {
      "id": "0x00989330c42e94baa5682f938ce209b70ae279998e11f23fa91627ef99b90ad9",
      "question": "LoL: Hanwha Life Esports vs DN SOOPers (BO1) - KeSPA Cup Group Stage",
      "volume": "395940.23445799993",
      "liquidity": "154105.6579",
      "end_date": "2026-07-21T18:30:00Z"
    },
    {
      "id": "0xdbca6b112a1c0c759ee3c8cb04aed49b641b6ed152ada9a5ea3ac374280a4852",
      "question": "Counter-Strike: M80 vs NIP - Map 1 Winner",
      "volume": "377850.7800299997",
      "liquidity": "250887.36726",
      "end_date": "2026-07-21T14:00:00Z"
    },
    {
      "id": "0x30f729ef18553d8956bfd7ae7a1e96dbad07e2476160239b23ec10e6cdc5f01b",
      "question": "Will Rodri win the 2026 Ballon d'Or?",
      "volume": "362651.17982900026",
      "liquidity": "96939.9184",
      "end_date": "2026-10-31T00:00:00Z"
    }
  ]
}