{
  "last_updated": "2026-07-18T16:56:54.866417+00:00",
  "markets": [
    {
      "id": "0x7c97f7315ac9a2e0eabe9b2b9caa8369feff95180483b5168a5274b69762690c",
      "question": "Will Belete Molla be the next Prime Minister of Ethiopia?",
      "volume": "23574963.62974601",
      "liquidity": "27531.26268",
      "end_date": "2026-06-01T00:00:00Z"
    },
    {
      "id": "0x6b049bc3befa02c22d0cfaee77625fc94e9a6d571f00c015ba7a3b442e306fbc",
      "question": "LoL: T1 vs Karmine Corp (BO3) - Esports World Cup Playoffs",
      "volume": "4620750.159960984",
      "liquidity": "1684114.32053",
      "end_date": "2026-07-18T17:00:00Z"
    },
    {
      "id": "0x0db7232eafb1882507f163f73655f262c6b84413f7567b0c0d105628cace065d",
      "question": "LoL: Gen.G vs Dplus KIA (BO3) - Esports World Cup Playoffs",
      "volume": "3244376.90576499",
      "liquidity": "185535.6118",
      "end_date": "2026-07-18T20:10:00Z"
    },
    {
      "id": "0xc41f543ccb7a1a35a200c28096cc2e5c2351c54546087f4f6cf5c4ef3e0c1aa5",
      "question": "Will France win on 2026-07-18?",
      "volume": "4247251.843257927",
      "liquidity": "3732477.7633",
      "end_date": "2026-07-18T21:00:00Z"
    },
    {
      "id": "0xaeec5397b4ee2ce20555c0099f0dcf4de4648a2f080c2d10b65ceaff9c26d7a8",
      "question": "France vs. England: Team to Win",
      "volume": "3648698.3461439125",
      "liquidity": "2135368.5515",
      "end_date": "2026-07-18T21:00:00Z"
    },
    {
      "id": "0x0c4cd2055d6ea89354ffddc55d6dbcef9355748112ea952fc925f3db6a5c457f",
      "question": "Will Argentina win the 2026 FIFA World Cup?",
      "volume": "158422396.02113217",
      "liquidity": "7130219.81505",
      "end_date": "2026-07-20T00:00:00Z"
    },
    {
      "id": "0x48aeb798c038759b99a87db0733aeca6aa31c8ca5292766afd410dfb9caca26b",
      "question": "LoL: Gen.G vs Dplus KIA - Game 1 Winner",
      "volume": "2052033.1394809983",
      "liquidity": "399162.70172",
      "end_date": "2026-07-18T20:10:00Z"
    },
    {
      "id": "0xf5ee4b6bd7d585c0e12e530074d0324493c302b82e127c832d15c89a610c0453",
      "question": "Will Demeke Mekonnen be the next Prime Minister of Ethiopia?",
      "volume": "14642384.913137998",
      "liquidity": "28712.3112",
      "end_date": "2026-06-01T00:00:00Z"
    },
    {
      "id": "0x4255afa1aae694dae73a3f9c898d720f1b21d1b25e040ba30a4cd7d11bbcb312",
      "question": "LoL: Gen.G vs Dplus KIA - Game 2 Winner",
      "volume": "1863958.327673004",
      "liquidity": "1208477.12228",
      "end_date": "2026-07-18T20:10:00Z"
    },
    {
      "id": "0x68bdc057bd18669f01b3e4b408d14733b2680a61c6e5c7a5cd5bdc86a1f41df6",
      "question": "Dota 2: Team Yandex vs PARIVISION - Game 2 Winner",
      "volume": "1631099.5168209975",
      "liquidity": "397901.582",
      "end_date": "2026-07-18T19:50:00Z"
    },
    {
      "id": "0x53da62774d757d6a651c69a1aca70f7765ed6b840bd1f4b209692f8d6c0c2d4e",
      "question": "Exact Score: Spain 2 - 3 Argentina?",
      "volume": "5327806.210680987",
      "liquidity": "2141612.3371",
      "end_date": "2026-07-19T19:00:00Z"
    },
    {
      "id": "0x7d9928e23aefb2209696048829b614f49e387d5a77327aa887d0724952fd1156",
      "question": "Will Hassan Shariatmadari be head of state in Iran end of 2026?",
      "volume": "1757612.8277880051",
      "liquidity": "49826.89853",
      "end_date": "2026-12-31T00:00:00Z"
    },
    {
      "id": "0xc186150831bc70982dfd374acc848fc51ae2bc4ab5b2fd037213deb5f46d9f44",
      "question": "Dota 2: Team Yandex vs PARIVISION (BO3) - Esports World Cup Playoffs",
      "volume": "1102824.0805739984",
      "liquidity": "156410.2155",
      "end_date": "2026-07-18T19:50:00Z"
    },
    {
      "id": "0x7976b8dbacf9077eb1453a62bcefd6ab2df199acd28aad276ff0d920d6992892",
      "question": "Will Spain win the 2026 FIFA World Cup?",
      "volume": "123794663.247236",
      "liquidity": "8477787.66258",
      "end_date": "2026-07-20T00:00:00Z"
    },
    {
      "id": "0x9beb4a4cab10c71d79f60beffd4a00a3016b4da7d82d6f18f64d5e80dd1691b2",
      "question": "Swedish Open: Andrey Rublev vs Alejandro Tabilo",
      "volume": "966933.5870140002",
      "liquidity": "575114.8689",
      "end_date": "2026-07-25T08:00:00Z"
    },
    {
      "id": "0xc69d4782ad01d89635d4a4140edc12a5db11434cc42fc275b16fc8e04a98cc83",
      "question": "Exact Score: France 2 - 1 England?",
      "volume": "1114767.6818619964",
      "liquidity": "2135705.0357",
      "end_date": "2026-07-18T21:00:00Z"
    },
    {
      "id": "0x4ede078cae84a5877ac32d7fb48811e5c23549a1904b7df06ff7935c6d79d831",
      "question": "Will the Fed decrease interest rates by 25 bps after the July 2026 meeting?",
      "volume": "11915419.23932811",
      "liquidity": "617134.46403",
      "end_date": "2026-07-29T00:00:00Z"
    },
    {
      "id": "0xaf12bd1a9ec448b428e5879f180b9b05d17cdf6a6af3c20d8a4b7327ca6bfd37",
      "question": "Will LeBron James play for the Golden State Warriors in 2026-27?",
      "volume": "3239201.0281709954",
      "liquidity": "83358.53934",
      "end_date": "2026-10-31T03:59:00Z"
    },
    {
      "id": "0x4b045e092c3166aa29d4864c11dffe7e316daafdac5677f11aa5cd16065fd042",
      "question": "Spain vs. Argentina: Team to Advance",
      "volume": "2294508.2734679966",
      "liquidity": "6730512.5567",
      "end_date": "2026-07-19T19:00:00Z"
    },
    {
      "id": "0x30cfb887558b20373a984da60c372fe5a90c0296aa6d8bb413a8aa7543846da2",
      "question": "Will Bernie Sanders win the 2028 Democratic presidential nomination?",
      "volume": "52124841.41277126",
      "liquidity": "1113590.78404",
      "end_date": "2028-11-07T00:00:00Z"
    }
  ]
}