{
  "last_updated": "2026-07-17T12:43:16.521678+00:00",
  "markets": [
    {
      "id": "0x7c97f7315ac9a2e0eabe9b2b9caa8369feff95180483b5168a5274b69762690c",
      "question": "Will Belete Molla be the next Prime Minister of Ethiopia?",
      "volume": "16652689.06774601",
      "liquidity": "29714.75908",
      "end_date": "2026-06-01T00:00:00Z"
    },
    {
      "id": "0xb6d6f15a1b5d08753653f1867ccd6126badfbe182a75159a330dc7b15336b309",
      "question": "Will Gedion Timothewos be the next Prime Minister of Ethiopia?",
      "volume": "55906710.34894003",
      "liquidity": "30813.48639",
      "end_date": "2026-06-01T00:00:00Z"
    },
    {
      "id": "0x0c4cd2055d6ea89354ffddc55d6dbcef9355748112ea952fc925f3db6a5c457f",
      "question": "Will Argentina win the 2026 FIFA World Cup?",
      "volume": "155348939.98089826",
      "liquidity": "8754066.53713",
      "end_date": "2026-07-20T00:00:00Z"
    },
    {
      "id": "0x53da62774d757d6a651c69a1aca70f7765ed6b840bd1f4b209692f8d6c0c2d4e",
      "question": "Exact Score: Spain 2 - 3 Argentina?",
      "volume": "3382719.260467997",
      "liquidity": "755151.46713",
      "end_date": "2026-07-19T19:00:00Z"
    },
    {
      "id": "0x7d0aaf81bbd3fd73b6a1651cce08a452c0cbf9c0cbb4520ce0f981065b639d88",
      "question": "Will Adanech Abiebie be the next Prime Minister of Ethiopia?",
      "volume": "43037124.695917025",
      "liquidity": "27405.9285",
      "end_date": "2026-06-01T00:00:00Z"
    },
    {
      "id": "0xf5ee4b6bd7d585c0e12e530074d0324493c302b82e127c832d15c89a610c0453",
      "question": "Will Demeke Mekonnen be the next Prime Minister of Ethiopia?",
      "volume": "10182661.434769997",
      "liquidity": "27279.16901",
      "end_date": "2026-06-01T00:00:00Z"
    },
    {
      "id": "0x7526f46b98feedea0c2497666aead4cb6b9a2949384f8e3e451c0e9f0f57468c",
      "question": "LoL: Hanwha Life Esports vs T1 (BO3) - Esports World Cup Playoffs",
      "volume": "1713670.5387249952",
      "liquidity": "180627.8366",
      "end_date": "2026-07-17T17:00:00Z"
    },
    {
      "id": "0x4266ab921148974f104cbadd099e13bca989441bf58acfd2a08fc6cc7440e1a1",
      "question": "Will Mohammad Khatami be head of state in Iran end of 2026?",
      "volume": "5000649.269269006",
      "liquidity": "58213.19088",
      "end_date": "2026-12-31T00:00:00Z"
    },
    {
      "id": "0xf9640023159d57007d91bf9f077c1bdedb11c2b9d9a26d750f7d3db79307ba39",
      "question": "Dota 2: Team Falcons vs Vici Gaming - Game 1 Winner",
      "volume": "1374735.9718549983",
      "liquidity": "718912.15731",
      "end_date": "2026-07-17T17:10:00Z"
    },
    {
      "id": "0x7976b8dbacf9077eb1453a62bcefd6ab2df199acd28aad276ff0d920d6992892",
      "question": "Will Spain win the 2026 FIFA World Cup?",
      "volume": "122345201.10940076",
      "liquidity": "9001676.52643",
      "end_date": "2026-07-20T00:00:00Z"
    },
    {
      "id": "0x9d407ed371fd904ef375724783d30eef0405e5d63d6bf1280d913b76492a035d",
      "question": "LoL: Hanwha Life Esports vs T1 - Game 1 Winner",
      "volume": "1257633.4175459985",
      "liquidity": "721444.95169",
      "end_date": "2026-07-17T15:00:00Z"
    },
    {
      "id": "0x691fb7c162635d7de42a18ad44b7b61042eeac8f0666b09220b653dfe480d1c7",
      "question": "LoL: Gen.G vs JD Gaming - Game 2 Winner",
      "volume": "1006452.4970140014",
      "liquidity": "1258826.84072",
      "end_date": "2026-07-17T17:00:00Z"
    },
    {
      "id": "0xcacd62d4b5a5d90fa55d31686ea558c166a9579d8d98def0bd09c4815e6bf901",
      "question": "Iasi Open: Yulia Putintseva vs Mayar Sherif",
      "volume": "954058.5735839998",
      "liquidity": "249458.4855",
      "end_date": "2026-07-24T07:00:00Z"
    },
    {
      "id": "0x4b045e092c3166aa29d4864c11dffe7e316daafdac5677f11aa5cd16065fd042",
      "question": "Spain vs. Argentina: Team to Advance",
      "volume": "1068262.2220229963",
      "liquidity": "5187416.9897",
      "end_date": "2026-07-19T19:00:00Z"
    },
    {
      "id": "0xaeec5397b4ee2ce20555c0099f0dcf4de4648a2f080c2d10b65ceaff9c26d7a8",
      "question": "France vs. England: Team to Win",
      "volume": "1061412.2651400166",
      "liquidity": "943234.8257",
      "end_date": "2026-07-18T21:00:00Z"
    },
    {
      "id": "0x962b62543a305b883233862f94d490b7dafd7ad2f845c62b287bd37519782da6",
      "question": "LoL: Gen.G vs JD Gaming (BO3) - Esports World Cup Playoffs",
      "volume": "883251.8210979995",
      "liquidity": "1317050.95444",
      "end_date": "2026-07-17T17:00:00Z"
    },
    {
      "id": "0x0c3e2d9d4be7868fa16e2bd452fec2c84cc576a5deeccea2278b1b80e07b0021",
      "question": "LoL: Hanwha Life Esports vs T1 - Game 2 Winner",
      "volume": "872534.6256669987",
      "liquidity": "106965.069",
      "end_date": "2026-07-17T15:00:00Z"
    },
    {
      "id": "0x4ede078cae84a5877ac32d7fb48811e5c23549a1904b7df06ff7935c6d79d831",
      "question": "Will the Fed decrease interest rates by 25 bps after the July 2026 meeting?",
      "volume": "10903516.585758073",
      "liquidity": "991172.45049",
      "end_date": "2026-07-29T00:00:00Z"
    },
    {
      "id": "0xc41f543ccb7a1a35a200c28096cc2e5c2351c54546087f4f6cf5c4ef3e0c1aa5",
      "question": "Will France win on 2026-07-18?",
      "volume": "1175675.253682001",
      "liquidity": "2276502.8858",
      "end_date": "2026-07-18T21:00:00Z"
    },
    {
      "id": "0x696576c9b20d20a71e0acd6f84d215f129fa361ed544b0df14f1ae540d84059f",
      "question": "Will Max Verstappen be the 2026 F1 Drivers' Champion?",
      "volume": "5058758.451779037",
      "liquidity": "206805.72137",
      "end_date": "2026-12-06T00:00:00Z"
    }
  ]
}