{
  "last_updated": "2026-07-12T22:45:49.756235+00:00",
  "whale_count": 50,
  "market_count": 20,
  "whales": [
    {
      "wallet": "0x3f6e93d1e2c2846a357276e29e7e9147e29c18d9",
      "name": "wco26",
      "score": 55.2,
      "roi_score": 75.7,
      "calibration_score": 50.0,
      "consistency_score": 50.0,
      "early_entry_score": 0.0,
      "volume_score": 100.0,
      "roi": 63.6,
      "cash_pnl": 299370.13,
      "realized_pnl": 171765.59,
      "total_usdc": 524481.5,
      "trade_count": 500,
      "market_count": 6,
      "position_count": 29,
      "resolved_count": 0,
      "win_rate": 0,
      "z_score": 0.0,
      "last_active": "2026-07-12T22:40:32+00:00",
      "top_markets": [
        "Will Argentina win the 2026 FIFA World Cup?",
        "Will England win the 2026 FIFA World Cup?",
        "Will Switzerland win the 2026 FIFA World Cup?"
      ],
      "signals": [
        {
          "market": "Will Spain win the 2026 FIFA World Cup?",
          "signal": "SKIP",
          "avg_price": 0.1047,
          "cur_price": 0.2045,
          "usdc_size": 311590.88,
          "outcome": "Yes"
        },
        {
          "market": "Will England win the 2026 FIFA World Cup?",
          "signal": "SKIP",
          "avg_price": 0.0572,
          "cur_price": 0.2145,
          "usdc_size": 156585.02,
          "outcome": "Yes"
        },
        {
          "market": "Will Argentina win the 2026 FIFA World Cup?",
          "signal": "SKIP",
          "avg_price": 0.0712,
          "cur_price": 0.1825,
          "usdc_size": 119491.46,
          "outcome": "Yes"
        },
        {
          "market": "Will France win the 2026 FIFA World Cup?",
          "signal": "SKIP",
          "avg_price": 0.0308,
          "cur_price": 0.3885,
          "usdc_size": 182595.11,
          "outcome": "Yes"
        }
      ]
    },
    {
      "wallet": "0x84cfffc3f16dcc353094de30d4a45226eccd2f63",
      "name": "mooseborzoi",
      "score": 50.0,
      "roi_score": 42.7,
      "calibration_score": 50.0,
      "consistency_score": 50.0,
      "early_entry_score": 43.8,
      "volume_score": 81.0,
      "roi": 14.1,
      "cash_pnl": 273486.94,
      "realized_pnl": 201628.53,
      "total_usdc": 41376.82,
      "trade_count": 500,
      "market_count": 17,
      "position_count": 186,
      "resolved_count": 0,
      "win_rate": 0,
      "z_score": 0.0,
      "last_active": "2026-07-12T22:45:08+00:00",
      "top_markets": [
        "France vs. Spain: Team to Advance",
        "Toronto Blue Jays vs. San Diego Padres",
        "Arizona Diamondbacks vs. Los Angeles Dodgers"
      ],
      "signals": [
        {
          "market": "France vs. Spain: Team to Advance",
          "signal": "ENTER",
          "avg_price": 0.6,
          "cur_price": 0.595,
          "usdc_size": 474292.12,
          "outcome": "France"
        },
        {
          "market": "France vs. Spain: Both Teams to Score",
          "signal": "ENTER",
          "avg_price": 0.5925,
          "cur_price": 0.585,
          "usdc_size": 49516.41,
          "outcome": "Yes"
        },
        {
          "market": "Will Argentina win the 2026 FIFA World Cup?",
          "signal": "LATE",
          "avg_price": 0.1759,
          "cur_price": 0.1825,
          "usdc_size": 269419.21,
          "outcome": "Yes"
        },
        {
          "market": "Exact Score: France 2 - 1 Spain?",
          "signal": "LATE",
          "avg_price": 0.1093,
          "cur_price": 0.105,
          "usdc_size": 3413.24,
          "outcome": "Yes"
        },
        {
          "market": "Will France win the 2026 FIFA World Cup?",
          "signal": "SKIP",
          "avg_price": 0.2818,
          "cur_price": 0.3885,
          "usdc_size": 744686.57,
          "outcome": "Yes"
        },
        {
          "market": "Will Spain win the 2026 FIFA World Cup?",
          "signal": "SKIP",
          "avg_price": 0.151,
          "cur_price": 0.2045,
          "usdc_size": 208733.56,
          "outcome": "Yes"
        },
        {
          "market": "Will England win the 2026 FIFA World Cup?",
          "signal": "SKIP",
          "avg_price": 0.1404,
          "cur_price": 0.2145,
          "usdc_size": 76866.94,
          "outcome": "Yes"
        },
        {
          "market": "Arizona Diamondbacks vs. Los Angeles Dodgers",
          "signal": "SKIP",
          "avg_price": 0.454,
          "cur_price": 0.615,
          "usdc_size": 8726.96,
          "outcome": "Arizona Diamondbacks"
        },
        {
          "market": "Toronto Blue Jays vs. San Diego Padres",
          "signal": "SKIP",
          "avg_price": 0.6367,
          "cur_price": 0.105,
          "usdc_size": 12370.8,
          "outcome": "San Diego Padres"
        },
        {
          "market": "Colorado Rockies vs. San Francisco Giants",
          "signal": "SKIP",
          "avg_price": 0.5845,
          "cur_price": 0.0005,
          "usdc_size": 7816.45,
          "outcome": "San Francisco Giants"
        },
        {
          "market": "Arizona Diamondbacks vs. Los Angeles Dodgers",
          "signal": "SKIP",
          "avg_price": 0.7403,
          "cur_price": 0.615,
          "usdc_size": 1750.94,
          "outcome": "Los Angeles Dodgers"
        }
      ]
    },
    {
      "wallet": "0xd224188a0bcf82d7c77a0c362da1f4313e095d09",
      "name": "0xd224188a0BCf82d7c77A0c362dA1F4313E095D09-1782876123088",
      "score": 49.7,
      "roi_score": 32.8,
      "calibration_score": 50.0,
      "consistency_score": 50.0,
      "early_entry_score": 78.5,
      "volume_score": 56.1,
      "roi": -0.8,
      "cash_pnl": -4.48,
      "realized_pnl": 0.0,
      "total_usdc": 1573.07,
      "trade_count": 2,
      "market_count": 2,
      "position_count": 1,
      "resolved_count": 0,
      "win_rate": 0,
      "z_score": 0.0,
      "last_active": "2026-07-12T22:34:07+00:00",
      "top_markets": [
        "France vs. Spain: Team to Advance",
        "UFC 329: Max Holloway vs. Conor McGregor (Welterweight, Main Card)"
      ],
      "signals": [
        {
          "market": "France vs. Spain: Team to Advance",
          "signal": "ENTER",
          "avg_price": 0.6,
          "cur_price": 0.595,
          "usdc_size": 532.65,
          "outcome": "France"
        }
      ]
    },
    {
      "wallet": "0xb2516845269865081e24f54708f4127d60de6f5b",
      "name": "3musketeers",
      "score": 45.5,
      "roi_score": 47.6,
      "calibration_score": 50.0,
      "consistency_score": 50.0,
      "early_entry_score": 0.0,
      "volume_score": 87.2,
      "roi": 21.5,
      "cash_pnl": 2512.23,
      "realized_pnl": -254.1,
      "total_usdc": 93556.61,
      "trade_count": 500,
      "market_count": 51,
      "position_count": 10,
      "resolved_count": 0,
      "win_rate": 0,
      "z_score": 0.0,
      "last_active": "2026-07-12T20:43:32+00:00",
      "top_markets": [
        "Will Argentina win on 2026-07-07?",
        "Will England win the 2026 FIFA World Cup?",
        "Will Norway win the 2026 FIFA World Cup?"
      ],
      "signals": [
        {
          "market": "Will England win the 2026 FIFA World Cup?",
          "signal": "SKIP",
          "avg_price": 0.1382,
          "cur_price": 0.2145,
          "usdc_size": 6692.35,
          "outcome": "Yes"
        },
        {
          "market": "Will Spain win the 2026 FIFA World Cup?",
          "signal": "SKIP",
          "avg_price": 0.1836,
          "cur_price": 0.2045,
          "usdc_size": 1226.4,
          "outcome": "Yes"
        },
        {
          "market": "Will Argentina win the 2026 FIFA World Cup?",
          "signal": "SKIP",
          "avg_price": 0.8043,
          "cur_price": 0.1825,
          "usdc_size": 4087.47,
          "outcome": "No"
        },
        {
          "market": "Will France win the 2026 FIFA World Cup?",
          "signal": "SKIP",
          "avg_price": 0.683,
          "cur_price": 0.3885,
          "usdc_size": 611.49,
          "outcome": "No"
        }
      ]
    },
    {
      "wallet": "0x89cd944aa9cf528142e3557099c6992eb7ce4d7d",
      "name": "",
      "score": 45.0,
      "roi_score": 44.8,
      "calibration_score": 50.0,
      "consistency_score": 50.0,
      "early_entry_score": 0.0,
      "volume_score": 91.1,
      "roi": 17.2,
      "cash_pnl": 16180.45,
      "realized_pnl": 4731.36,
      "total_usdc": 155637.3,
      "trade_count": 500,
      "market_count": 11,
      "position_count": 20,
      "resolved_count": 0,
      "win_rate": 0,
      "z_score": 0.0,
      "last_active": "2026-07-12T19:42:04+00:00",
      "top_markets": [
        "Exact Score: Norway 2 - 3 England?",
        "Exact Score: Argentina 3 - 2 Switzerland?",
        "Will Spain win the 2026 FIFA World Cup?"
      ],
      "signals": [
        {
          "market": "Will France win the 2026 FIFA World Cup?",
          "signal": "SKIP",
          "avg_price": 0.3298,
          "cur_price": 0.3885,
          "usdc_size": 79845.86,
          "outcome": "Yes"
        },
        {
          "market": "Will Spain win the 2026 FIFA World Cup?",
          "signal": "SKIP",
          "avg_price": 0.1851,
          "cur_price": 0.2045,
          "usdc_size": 2616.51,
          "outcome": "Yes"
        },
        {
          "market": "Will England win the 2026 FIFA World Cup?",
          "signal": "SKIP",
          "avg_price": 0.7846,
          "cur_price": 0.2145,
          "usdc_size": 6284.04,
          "outcome": "No"
        }
      ]
    },
    {
      "wallet": "0x54f65775fb4303584ea357fcabf681547ce2b0f2",
      "name": "Zotopanxl1000",
      "score": 43.5,
      "roi_score": 38.5,
      "calibration_score": 50.0,
      "consistency_score": 50.0,
      "early_entry_score": 0.0,
      "volume_score": 94.2,
      "roi": 7.8,
      "cash_pnl": 454.81,
      "realized_pnl": 140.41,
      "total_usdc": 233196.29,
      "trade_count": 500,
      "market_count": 199,
      "position_count": 2,
      "resolved_count": 0,
      "win_rate": 0,
      "z_score": 0.0,
      "last_active": "2026-07-12T20:04:23+00:00",
      "top_markets": [
        "Portugal vs. Nigeria: O/U 2.5",
        "Argentina vs. Cabo Verde: Team to Advance",
        "Will Brazil be eliminated in the Round of 32 of the World Cup?"
      ],
      "signals": [
        {
          "market": "Will Argentina win the 2026 FIFA World Cup?",
          "signal": "LATE",
          "avg_price": 0.1947,
          "cur_price": 0.1825,
          "usdc_size": 1457.14,
          "outcome": "Yes"
        },
        {
          "market": "Will France win the 2026 FIFA World Cup?",
          "signal": "SKIP",
          "avg_price": 0.344,
          "cur_price": 0.3885,
          "usdc_size": 4832.94,
          "outcome": "Yes"
        }
      ]
    },
    {
      "wallet": "0xcbba64cddd05171925ffd05d8f8abd38c83fdbff",
      "name": "HOG993",
      "score": 43.5,
      "roi_score": 4.8,
      "calibration_score": 50.0,
      "consistency_score": 50.0,
      "early_entry_score": 79.2,
      "volume_score": 77.1,
      "roi": -42.8,
      "cash_pnl": -83323.0,
      "realized_pnl": -1735635.38,
      "total_usdc": 24833.71,
      "trade_count": 500,
      "market_count": 5,
      "position_count": 198,
      "resolved_count": 0,
      "win_rate": 0,
      "z_score": 0.0,
      "last_active": "2026-07-12T22:44:32+00:00",
      "top_markets": [
        "France vs. Spain: Team to Advance",
        "Exact Score: France 2 - 1 Spain?",
        "Will France win on 2026-07-14?"
      ],
      "signals": [
        {
          "market": "Will France win on 2026-07-14?",
          "signal": "LATE",
          "avg_price": 0.4415,
          "cur_price": 0.415,
          "usdc_size": 35404.34,
          "outcome": "Yes"
        },
        {
          "market": "France vs. Spain: Team to Advance",
          "signal": "SKIP",
          "avg_price": 0.4,
          "cur_price": 0.595,
          "usdc_size": 27612.32,
          "outcome": "Spain"
        },
        {
          "market": "Will Spain win the 2026 FIFA World Cup?",
          "signal": "SKIP",
          "avg_price": 0.0236,
          "cur_price": 0.2045,
          "usdc_size": 7752.86,
          "outcome": "Yes"
        },
        {
          "market": "Will France vs. Spain end in a draw?",
          "signal": "SKIP",
          "avg_price": 0.3333,
          "cur_price": 0.295,
          "usdc_size": 8850.0,
          "outcome": "Yes"
        }
      ]
    },
    {
      "wallet": "0xbfe23d7adb6f6108dba269d7e8f275675f531913",
      "name": "justT",
      "score": 43.0,
      "roi_score": 41.9,
      "calibration_score": 50.0,
      "consistency_score": 50.0,
      "early_entry_score": 0.0,
      "volume_score": 79.4,
      "roi": 12.9,
      "cash_pnl": 525.92,
      "realized_pnl": 142.5,
      "total_usdc": 33385.16,
      "trade_count": 100,
      "market_count": 13,
      "position_count": 7,
      "resolved_count": 0,
      "win_rate": 0,
      "z_score": 0.0,
      "last_active": "2026-07-12T21:02:40+00:00",
      "top_markets": [
        "Will Netherlands win the 2026 FIFA World Cup?",
        "Strait of Hormuz traffic returns to normal by July 31?",
        "Will A Nation That Has Never Won the World Cup Win in 2026?"
      ],
      "signals": [
        {
          "market": "Will Argentina win the 2026 FIFA World Cup?",
          "signal": "LATE",
          "avg_price": 0.194,
          "cur_price": 0.1825,
          "usdc_size": 547.5,
          "outcome": "Yes"
        }
      ]
    },
    {
      "wallet": "0x769b47d3ceae223ab14aec22ebd8c9260ee02ea9",
      "name": "Kentincome",
      "score": 42.9,
      "roi_score": 0.0,
      "calibration_score": 50.0,
      "consistency_score": 50.0,
      "early_entry_score": 78.7,
      "volume_score": 85.8,
      "roi": -93.2,
      "cash_pnl": -19847.63,
      "realized_pnl": -322.97,
      "total_usdc": 77803.59,
      "trade_count": 374,
      "market_count": 211,
      "position_count": 84,
      "resolved_count": 0,
      "win_rate": 0,
      "z_score": 0.0,
      "last_active": "2026-07-12T22:15:26+00:00",
      "top_markets": [
        "Bitcoin Up or Down - February 21, 7:25PM-7:30PM ET",
        "Bitcoin Up or Down - February 20, 11:30PM-11:35PM ET",
        "Will Aston Villa FC vs. West Ham United FC end in a draw?"
      ],
      "signals": [
        {
          "market": "France vs. Spain: Team to Advance",
          "signal": "ENTER",
          "avg_price": 0.6,
          "cur_price": 0.595,
          "usdc_size": 1457.75,
          "outcome": "France"
        }
      ]
    },
    {
      "wallet": "0xd19c705d926a60527249dad58bdf726f5b40fdd0",
      "name": "mv.savvy",
      "score": 42.5,
      "roi_score": 0.0,
      "calibration_score": 50.0,
      "consistency_score": 50.0,
      "early_entry_score": 78.9,
      "volume_score": 82.0,
      "roi": -84.3,
      "cash_pnl": -7802.67,
      "realized_pnl": 0.0,
      "total_usdc": 46959.14,
      "trade_count": 115,
      "market_count": 54,
      "position_count": 13,
      "resolved_count": 0,
      "win_rate": 0,
      "z_score": 0.0,
      "last_active": "2026-07-12T21:52:50+00:00",
      "top_markets": [
        "Knicks vs. Spurs",
        "Spurs vs. Knicks",
        "Will Giannis Antetokounmpo play for the Milwaukee Bucks in 2026-27?"
      ],
      "signals": [
        {
          "market": "France vs. Spain: Team to Advance",
          "signal": "ENTER",
          "avg_price": 0.6,
          "cur_price": 0.595,
          "usdc_size": 1457.75,
          "outcome": "France"
        }
      ]
    },
    {
      "wallet": "0xb10047d6a254b2ebb306d7a7d13bf59171ab6461",
      "name": "Parz1vaI",
      "score": 42.2,
      "roi_score": 33.8,
      "calibration_score": 50.0,
      "consistency_score": 50.0,
      "early_entry_score": 0.0,
      "volume_score": 96.0,
      "roi": 0.7,
      "cash_pnl": 2112.02,
      "realized_pnl": 36629.28,
      "total_usdc": 295796.85,
      "trade_count": 500,
      "market_count": 40,
      "position_count": 79,
      "resolved_count": 0,
      "win_rate": 0,
      "z_score": 0.0,
      "last_active": "2026-07-12T22:44:10+00:00",
      "top_markets": [
        "Will the announcers say \"Nutmeg\" or \"Meg\" during the Norway vs England FIFA World Cup Match?",
        "LoL: Bilibili Gaming vs Hanwha Life Esports (BO5) - Mid-Season Invitational Playoffs",
        "President Trump to Attend World Cup Final?"
      ],
      "signals": [
        {
          "market": "Will France win the 2026 FIFA World Cup?",
          "signal": "SKIP",
          "avg_price": 0.3441,
          "cur_price": 0.3885,
          "usdc_size": 8673.58,
          "outcome": "Yes"
        },
        {
          "market": "Will England win the 2026 FIFA World Cup?",
          "signal": "SKIP",
          "avg_price": 0.1164,
          "cur_price": 0.2145,
          "usdc_size": 2874.57,
          "outcome": "Yes"
        }
      ]
    },
    {
      "wallet": "0xcecaeade076dafc88fdb955864da9d9c15693f67",
      "name": "Everestpredictions",
      "score": 42.0,
      "roi_score": 34.4,
      "calibration_score": 50.0,
      "consistency_score": 50.0,
      "early_entry_score": 0.0,
      "volume_score": 91.6,
      "roi": 1.7,
      "cash_pnl": 688.03,
      "realized_pnl": 7.2,
      "total_usdc": 165840.24,
      "trade_count": 500,
      "market_count": 141,
      "position_count": 27,
      "resolved_count": 0,
      "win_rate": 0,
      "z_score": 0.0,
      "last_active": "2026-07-12T22:39:52+00:00",
      "top_markets": [
        "Will SpaceX have the highest IPO Market Cap 2026?",
        "Will Erling Haaland be the top goalscorer at the 2026 FIFA World Cup?",
        "Aleksandar Vu\u010di\u0107 out as Serbian President by June 30, 2026?"
      ],
      "signals": [
        {
          "market": "Strait of Hormuz traffic returns to normal by July 15?",
          "signal": "SKIP",
          "avg_price": 0.8732,
          "cur_price": 0.0035,
          "usdc_size": 2282.29,
          "outcome": "No"
        },
        {
          "market": "Will Argentina win the 2026 FIFA World Cup?",
          "signal": "SKIP",
          "avg_price": 0.8189,
          "cur_price": 0.1825,
          "usdc_size": 798.53,
          "outcome": "No"
        }
      ]
    },
    {
      "wallet": "0xa8c63f775ddbbe66b56614191747def3021444e8",
      "name": "Tenebrus7",
      "score": 41.7,
      "roi_score": 34.1,
      "calibration_score": 50.0,
      "consistency_score": 50.0,
      "early_entry_score": 0.0,
      "volume_score": 90.1,
      "roi": 1.1,
      "cash_pnl": 2957.05,
      "realized_pnl": -23520.53,
      "total_usdc": 136955.74,
      "trade_count": 500,
      "market_count": 55,
      "position_count": 175,
      "resolved_count": 0,
      "win_rate": 0,
      "z_score": 0.0,
      "last_active": "2026-07-12T22:41:43+00:00",
      "top_markets": [
        "President Trump to Attend World Cup Final?",
        "Will Count Binface win the Clacton by-election?",
        "US-Iran 60 day negotiation period extended?"
      ],
      "signals": [
        {
          "market": "Will the U.S. invade Iran before 2027?",
          "signal": "SKIP",
          "avg_price": 0.8579,
          "cur_price": 0.165,
          "usdc_size": 10019.96,
          "outcome": "No"
        },
        {
          "market": "Iran full airspace closure by July 15?",
          "signal": "SKIP",
          "avg_price": 0.8879,
          "cur_price": 0.086,
          "usdc_size": 1554.66,
          "outcome": "No"
        }
      ]
    },
    {
      "wallet": "0xadec0c1c1991e9dd0bdcf9401479614b65b43c7b",
      "name": "DoubleDip",
      "score": 41.2,
      "roi_score": 34.3,
      "calibration_score": 50.0,
      "consistency_score": 50.0,
      "early_entry_score": 0.0,
      "volume_score": 84.3,
      "roi": 1.4,
      "cash_pnl": 542.08,
      "realized_pnl": 15572.26,
      "total_usdc": 64036.87,
      "trade_count": 500,
      "market_count": 22,
      "position_count": 94,
      "resolved_count": 0,
      "win_rate": 0,
      "z_score": 0.0,
      "last_active": "2026-07-12T22:35:58+00:00",
      "top_markets": [
        "Will France win the 2026 FIFA World Cup?",
        "Will England win the 2026 FIFA World Cup?",
        "Will Spain win the 2026 FIFA World Cup?"
      ],
      "signals": [
        {
          "market": "Will France win the 2026 FIFA World Cup?",
          "signal": "ENTER",
          "avg_price": 0.3882,
          "cur_price": 0.3885,
          "usdc_size": 16403.24,
          "outcome": "Yes"
        }
      ]
    },
    {
      "wallet": "0xd3a72382f2c459af33a839866b3f2852e4723362",
      "name": "Pol.1",
      "score": 41.2,
      "roi_score": 33.3,
      "calibration_score": 50.0,
      "consistency_score": 50.0,
      "early_entry_score": 0.0,
      "volume_score": 87.1,
      "roi": -0.0,
      "cash_pnl": -8.98,
      "realized_pnl": -2955.19,
      "total_usdc": 92594.63,
      "trade_count": 500,
      "market_count": 6,
      "position_count": 14,
      "resolved_count": 0,
      "win_rate": 0,
      "z_score": 0.0,
      "last_active": "2026-07-12T22:44:32+00:00",
      "top_markets": [
        "Will France win the 2026 FIFA World Cup?",
        "Will Argentina win the 2026 FIFA World Cup?",
        "Will Spain win the 2026 FIFA World Cup?"
      ],
      "signals": [
        {
          "market": "Will France win the 2026 FIFA World Cup?",
          "signal": "ENTER",
          "avg_price": 0.3879,
          "cur_price": 0.3885,
          "usdc_size": 1955.32,
          "outcome": "Yes"
        },
        {
          "market": "Will France win the 2026 FIFA World Cup?",
          "signal": "SKIP",
          "avg_price": 0.611,
          "cur_price": 0.3885,
          "usdc_size": 6114.97,
          "outcome": "No"
        },
        {
          "market": "Will Spain win the 2026 FIFA World Cup?",
          "signal": "SKIP",
          "avg_price": 0.799,
          "cur_price": 0.2045,
          "usdc_size": 3977.5,
          "outcome": "No"
        },
        {
          "market": "Will England win the 2026 FIFA World Cup?",
          "signal": "SKIP",
          "avg_price": 0.7849,
          "cur_price": 0.2145,
          "usdc_size": 3142.0,
          "outcome": "No"
        },
        {
          "market": "Will Argentina win the 2026 FIFA World Cup?",
          "signal": "SKIP",
          "avg_price": 0.8179,
          "cur_price": 0.1825,
          "usdc_size": 3270.0,
          "outcome": "No"
        }
      ]
    },
    {
      "wallet": "0x00c419b3f6415911abe859fcb70b7a3cf2f492c2",
      "name": "kitty118",
      "score": 41.1,
      "roi_score": 33.1,
      "calibration_score": 50.0,
      "consistency_score": 50.0,
      "early_entry_score": 0.0,
      "volume_score": 86.9,
      "roi": -0.4,
      "cash_pnl": -72.56,
      "realized_pnl": 85381.35,
      "total_usdc": 89998.88,
      "trade_count": 500,
      "market_count": 4,
      "position_count": 58,
      "resolved_count": 0,
      "win_rate": 0,
      "z_score": 0.0,
      "last_active": "2026-07-12T22:44:49+00:00",
      "top_markets": [
        "Will France win the 2026 FIFA World Cup?",
        "Will Argentina win the 2026 FIFA World Cup?",
        "Will England win the 2026 FIFA World Cup?"
      ],
      "signals": [
        {
          "market": "Will England win the 2026 FIFA World Cup?",
          "signal": "SKIP",
          "avg_price": 0.785,
          "cur_price": 0.2145,
          "usdc_size": 6284.0,
          "outcome": "No"
        },
        {
          "market": "Will France win the 2026 FIFA World Cup?",
          "signal": "SKIP",
          "avg_price": 0.611,
          "cur_price": 0.3885,
          "usdc_size": 4891.99,
          "outcome": "No"
        },
        {
          "market": "Will Spain win the 2026 FIFA World Cup?",
          "signal": "SKIP",
          "avg_price": 0.795,
          "cur_price": 0.2045,
          "usdc_size": 5939.5,
          "outcome": "No"
        },
        {
          "market": "Will Argentina win the 2026 FIFA World Cup?",
          "signal": "SKIP",
          "avg_price": 0.8179,
          "cur_price": 0.1825,
          "usdc_size": 3419.58,
          "outcome": "No"
        }
      ]
    },
    {
      "wallet": "0xa76cabeeb7e7dffc7e96e4c0a9bf23d7df97dc83",
      "name": "Juampikk",
      "score": 41.1,
      "roi_score": 33.5,
      "calibration_score": 50.0,
      "consistency_score": 50.0,
      "early_entry_score": 0.0,
      "volume_score": 85.1,
      "roi": 0.3,
      "cash_pnl": 1.99,
      "realized_pnl": -156.92,
      "total_usdc": 70607.33,
      "trade_count": 500,
      "market_count": 285,
      "position_count": 1,
      "resolved_count": 0,
      "win_rate": 0,
      "z_score": 0.0,
      "last_active": "2026-07-12T22:33:08+00:00",
      "top_markets": [
        "Will Argentina win the 2026 FIFA World Cup?",
        "Will Brazil win the 2026 FIFA World Cup?",
        "Will Lando Norris win the 2026 F1 Canadian Grand Prix?"
      ],
      "signals": [
        {
          "market": "Will Argentina win the 2026 FIFA World Cup?",
          "signal": "ENTER",
          "avg_price": 0.1819,
          "cur_price": 0.1825,
          "usdc_size": 723.92,
          "outcome": "Yes"
        }
      ]
    },
    {
      "wallet": "0x6c08208c8f6c69b7198eea0f9fcd1dc2f5f15c69",
      "name": "zoltar02",
      "score": 41.1,
      "roi_score": 33.4,
      "calibration_score": 50.0,
      "consistency_score": 50.0,
      "early_entry_score": 0.0,
      "volume_score": 85.8,
      "roi": 0.1,
      "cash_pnl": 25.98,
      "realized_pnl": 31328.73,
      "total_usdc": 77843.62,
      "trade_count": 500,
      "market_count": 10,
      "position_count": 32,
      "resolved_count": 0,
      "win_rate": 0,
      "z_score": 0.0,
      "last_active": "2026-07-12T22:44:49+00:00",
      "top_markets": [
        "LoL: Bilibili Gaming vs Hanwha Life Esports (BO5) - Mid-Season Invitational Playoffs",
        "Will Argentina win the 2026 FIFA World Cup?",
        "Will Spain win the 2026 FIFA World Cup?"
      ],
      "signals": [
        {
          "market": "Will Spain win the 2026 FIFA World Cup?",
          "signal": "ENTER",
          "avg_price": 0.2039,
          "cur_price": 0.2045,
          "usdc_size": 1657.1,
          "outcome": "Yes"
        },
        {
          "market": "Will Argentina win the 2026 FIFA World Cup?",
          "signal": "ENTER",
          "avg_price": 0.1829,
          "cur_price": 0.1825,
          "usdc_size": 1095.01,
          "outcome": "Yes"
        },
        {
          "market": "Will Spain win the 2026 FIFA World Cup?",
          "signal": "SKIP",
          "avg_price": 0.795,
          "cur_price": 0.2045,
          "usdc_size": 6364.0,
          "outcome": "No"
        },
        {
          "market": "Will France vs. Spain end in a draw?",
          "signal": "SKIP",
          "avg_price": 0.7,
          "cur_price": 0.295,
          "usdc_size": 4230.0,
          "outcome": "No"
        },
        {
          "market": "Will Argentina win the 2026 FIFA World Cup?",
          "signal": "SKIP",
          "avg_price": 0.8179,
          "cur_price": 0.1825,
          "usdc_size": 4904.91,
          "outcome": "No"
        },
        {
          "market": "Will England win the 2026 FIFA World Cup?",
          "signal": "SKIP",
          "avg_price": 0.785,
          "cur_price": 0.2145,
          "usdc_size": 2558.14,
          "outcome": "No"
        },
        {
          "market": "Will France win the 2026 FIFA World Cup?",
          "signal": "SKIP",
          "avg_price": 0.611,
          "cur_price": 0.3885,
          "usdc_size": 1223.0,
          "outcome": "No"
        }
      ]
    },
    {
      "wallet": "0xaf2a0ae1554c24a7146ff676e6c4bd80519464dd",
      "name": "dsafhhj",
      "score": 41.0,
      "roi_score": 32.8,
      "calibration_score": 50.0,
      "consistency_score": 50.0,
      "early_entry_score": 0.0,
      "volume_score": 86.2,
      "roi": -0.8,
      "cash_pnl": -93.16,
      "realized_pnl": -93635.57,
      "total_usdc": 81653.99,
      "trade_count": 500,
      "market_count": 4,
      "position_count": 40,
      "resolved_count": 0,
      "win_rate": 0,
      "z_score": 0.0,
      "last_active": "2026-07-12T22:27:32+00:00",
      "top_markets": [
        "Will France win the 2026 FIFA World Cup?",
        "Will England win the 2026 FIFA World Cup?",
        "Will Argentina win the 2026 FIFA World Cup?"
      ],
      "signals": [
        {
          "market": "Will England win the 2026 FIFA World Cup?",
          "signal": "SKIP",
          "avg_price": 0.785,
          "cur_price": 0.2145,
          "usdc_size": 3927.5,
          "outcome": "No"
        },
        {
          "market": "Will Spain win the 2026 FIFA World Cup?",
          "signal": "SKIP",
          "avg_price": 0.797,
          "cur_price": 0.2045,
          "usdc_size": 3977.21,
          "outcome": "No"
        },
        {
          "market": "Will Argentina win the 2026 FIFA World Cup?",
          "signal": "SKIP",
          "avg_price": 0.8179,
          "cur_price": 0.1825,
          "usdc_size": 4086.89,
          "outcome": "No"
        }
      ]
    },
    {
      "wallet": "0xd49184191139f35dc81b34601b4d96cf46007812",
      "name": "h928888",
      "score": 40.9,
      "roi_score": 32.5,
      "calibration_score": 50.0,
      "consistency_score": 50.0,
      "early_entry_score": 0.0,
      "volume_score": 86.3,
      "roi": -1.2,
      "cash_pnl": -58.04,
      "realized_pnl": -43018.05,
      "total_usdc": 83001.28,
      "trade_count": 500,
      "market_count": 5,
      "position_count": 36,
      "resolved_count": 0,
      "win_rate": 0,
      "z_score": 0.0,
      "last_active": "2026-07-12T22:44:49+00:00",
      "top_markets": [
        "Wimbledon ATP: Jannik Sinner vs Alexander Zverev",
        "Will Argentina win the 2026 FIFA World Cup?",
        "Will France win the 2026 FIFA World Cup?"
      ],
      "signals": [
        {
          "market": "Will Spain win the 2026 FIFA World Cup?",
          "signal": "SKIP",
          "avg_price": 0.795,
          "cur_price": 0.2045,
          "usdc_size": 1594.24,
          "outcome": "No"
        },
        {
          "market": "Will Argentina win the 2026 FIFA World Cup?",
          "signal": "SKIP",
          "avg_price": 0.8169,
          "cur_price": 0.1825,
          "usdc_size": 1634.56,
          "outcome": "No"
        },
        {
          "market": "Will England win the 2026 FIFA World Cup?",
          "signal": "SKIP",
          "avg_price": 0.7849,
          "cur_price": 0.2145,
          "usdc_size": 1570.21,
          "outcome": "No"
        }
      ]
    },
    {
      "wallet": "0x9826f49b68cc753032600fe40b9ca21ca410e7fe",
      "name": "FMANTENNA",
      "score": 40.9,
      "roi_score": 32.1,
      "calibration_score": 50.0,
      "consistency_score": 50.0,
      "early_entry_score": 0.0,
      "volume_score": 88.0,
      "roi": -1.9,
      "cash_pnl": -1198.15,
      "realized_pnl": -90.29,
      "total_usdc": 103329.55,
      "trade_count": 500,
      "market_count": 50,
      "position_count": 26,
      "resolved_count": 0,
      "win_rate": 0,
      "z_score": 0.0,
      "last_active": "2026-07-12T19:44:14+00:00",
      "top_markets": [
        "Will England win on 2026-06-27?",
        "Will Andy Burnham be the next Prime Minister of the United Kingdom in 2026?",
        "Will Germany win on 2026-06-29?"
      ],
      "signals": [
        {
          "market": "Will France win the 2026 FIFA World Cup?",
          "signal": "SKIP",
          "avg_price": 0.7073,
          "cur_price": 0.3885,
          "usdc_size": 14431.4,
          "outcome": "No"
        },
        {
          "market": "Will Argentina win the 2026 FIFA World Cup?",
          "signal": "SKIP",
          "avg_price": 0.8254,
          "cur_price": 0.1825,
          "usdc_size": 13622.43,
          "outcome": "No"
        },
        {
          "market": "Will Spain win the 2026 FIFA World Cup?",
          "signal": "SKIP",
          "avg_price": 0.101,
          "cur_price": 0.2045,
          "usdc_size": 2044.0,
          "outcome": "Yes"
        },
        {
          "market": "Will England win the 2026 FIFA World Cup?",
          "signal": "SKIP",
          "avg_price": 0.1549,
          "cur_price": 0.2145,
          "usdc_size": 1716.0,
          "outcome": "Yes"
        }
      ]
    },
    {
      "wallet": "0x900e3c7bc26b51dfd607cd152e8ffadbe11aa4d3",
      "name": "ivanx4k",
      "score": 40.5,
      "roi_score": 29.7,
      "calibration_score": 50.0,
      "consistency_score": 50.0,
      "early_entry_score": 0.0,
      "volume_score": 91.1,
      "roi": -5.4,
      "cash_pnl": -167.08,
      "realized_pnl": 105.6,
      "total_usdc": 155257.86,
      "trade_count": 500,
      "market_count": 127,
      "position_count": 5,
      "resolved_count": 0,
      "win_rate": 0,
      "z_score": 0.0,
      "last_active": "2026-07-12T22:36:59+00:00",
      "top_markets": [
        "Will Bitcoin reach $67,500 in June?",
        "Will Bitcoin reach $75,000 in July?",
        "Will Bitcoin dip to $50,000 in June?"
      ],
      "signals": [
        {
          "market": "Will Argentina win the 2026 FIFA World Cup?",
          "signal": "SKIP",
          "avg_price": 0.8179,
          "cur_price": 0.1825,
          "usdc_size": 1528.73,
          "outcome": "No"
        }
      ]
    },
    {
      "wallet": "0x5811c8ad5dc5990528357ecf1a6d03311d6c0976",
      "name": "0x5811c8AD5DC5990528357ecf1A6D03311D6c0976-1782550886071",
      "score": 40.5,
      "roi_score": 0.0,
      "calibration_score": 50.0,
      "consistency_score": 50.0,
      "early_entry_score": 62.8,
      "volume_score": 86.0,
      "roi": -81.7,
      "cash_pnl": -78372.79,
      "realized_pnl": 119413.23,
      "total_usdc": 79605.1,
      "trade_count": 500,
      "market_count": 83,
      "position_count": 255,
      "resolved_count": 0,
      "win_rate": 0,
      "z_score": 0.0,
      "last_active": "2026-07-12T22:40:59+00:00",
      "top_markets": [
        "France vs. Spain: Team to Advance",
        "Will Spain win on 2026-07-14?",
        "Boston Red Sox vs. New York Mets"
      ],
      "signals": [
        {
          "market": "Will France win on 2026-07-14?",
          "signal": "ENTER",
          "avg_price": 0.4133,
          "cur_price": 0.415,
          "usdc_size": 566.48,
          "outcome": "Yes"
        },
        {
          "market": "France vs. Spain: Both Teams to Score",
          "signal": "ENTER",
          "avg_price": 0.5951,
          "cur_price": 0.585,
          "usdc_size": 711.16,
          "outcome": "Yes"
        },
        {
          "market": "France vs. Spain: O/U 2.5",
          "signal": "LATE",
          "avg_price": 0.4848,
          "cur_price": 0.515,
          "usdc_size": 1796.9,
          "outcome": "Under"
        },
        {
          "market": "France vs. Spain: Team to Advance",
          "signal": "SKIP",
          "avg_price": 0.4,
          "cur_price": 0.595,
          "usdc_size": 2606.19,
          "outcome": "Spain"
        },
        {
          "market": "Exact Score: France 2 - 1 Spain?",
          "signal": "SKIP",
          "avg_price": 0.8919,
          "cur_price": 0.105,
          "usdc_size": 1562.62,
          "outcome": "No"
        },
        {
          "market": "Toronto Blue Jays vs. San Diego Padres",
          "signal": "SKIP",
          "avg_price": 0.45,
          "cur_price": 0.105,
          "usdc_size": 970.12,
          "outcome": "San Diego Padres"
        }
      ]
    },
    {
      "wallet": "0xfea85cf0cc9720686309a85fba659fc1cd8047aa",
      "name": "",
      "score": 40.0,
      "roi_score": 27.5,
      "calibration_score": 50.0,
      "consistency_score": 50.0,
      "early_entry_score": 0.0,
      "volume_score": 92.2,
      "roi": -8.8,
      "cash_pnl": -1005.44,
      "realized_pnl": 0.04,
      "total_usdc": 178847.85,
      "trade_count": 500,
      "market_count": 31,
      "position_count": 8,
      "resolved_count": 0,
      "win_rate": 0,
      "z_score": 0.0,
      "last_active": "2026-07-12T20:00:07+00:00",
      "top_markets": [
        "Will Norway win the 2026 FIFA World Cup?",
        "ODI Series Zimbabwe vs Bangladesh: Zimbabwe vs Bangladesh",
        "Major League Cricket: Mi New York vs Seattle Orcas"
      ],
      "signals": []
    },
    {
      "wallet": "0x936e3a446b995b0cf997e583c92bbd125919473f",
      "name": "overbet",
      "score": 39.6,
      "roi_score": 23.7,
      "calibration_score": 50.0,
      "consistency_score": 50.0,
      "early_entry_score": 0.0,
      "volume_score": 100.0,
      "roi": -14.5,
      "cash_pnl": -12427.53,
      "realized_pnl": 7.61,
      "total_usdc": 514380.49,
      "trade_count": 500,
      "market_count": 50,
      "position_count": 20,
      "resolved_count": 0,
      "win_rate": 0,
      "z_score": 0.0,
      "last_active": "2026-07-12T22:37:44+00:00",
      "top_markets": [
        "Exact Score: Brazil 0 - 2 Norway?",
        "Argentina leading at halftime?",
        "Exact Score: Norway 1 - 0 England?"
      ],
      "signals": [
        {
          "market": "Will Spain win the 2026 FIFA World Cup?",
          "signal": "ENTER",
          "avg_price": 0.205,
          "cur_price": 0.2045,
          "usdc_size": 14644.87,
          "outcome": "Yes"
        },
        {
          "market": "Will Argentina win the 2026 FIFA World Cup?",
          "signal": "ENTER",
          "avg_price": 0.182,
          "cur_price": 0.1825,
          "usdc_size": 13075.77,
          "outcome": "Yes"
        },
        {
          "market": "Will England win the 2026 FIFA World Cup?",
          "signal": "ENTER",
          "avg_price": 0.215,
          "cur_price": 0.2145,
          "usdc_size": 15368.48,
          "outcome": "Yes"
        },
        {
          "market": "Will France win the 2026 FIFA World Cup?",
          "signal": "ENTER",
          "avg_price": 0.389,
          "cur_price": 0.3885,
          "usdc_size": 27835.08,
          "outcome": "Yes"
        }
      ]
    },
    {
      "wallet": "0x8b016395230775d54a3cd81d2e254653549124a9",
      "name": "ac009",
      "score": 39.6,
      "roi_score": 29.2,
      "calibration_score": 50.0,
      "consistency_score": 50.0,
      "early_entry_score": 0.0,
      "volume_score": 83.2,
      "roi": -6.3,
      "cash_pnl": -180.01,
      "realized_pnl": -291.22,
      "total_usdc": 55418.61,
      "trade_count": 500,
      "market_count": 8,
      "position_count": 5,
      "resolved_count": 0,
      "win_rate": 0,
      "z_score": 0.0,
      "last_active": "2026-07-12T22:33:04+00:00",
      "top_markets": [
        "Will France win the 2026 FIFA World Cup?",
        "Will Jude Bellingham be the top goalscorer at the 2026 FIFA World Cup?",
        "Will Argentina win the 2026 FIFA World Cup?"
      ],
      "signals": [
        {
          "market": "Will France win the 2026 FIFA World Cup?",
          "signal": "SKIP",
          "avg_price": 0.611,
          "cur_price": 0.3885,
          "usdc_size": 600.5,
          "outcome": "No"
        },
        {
          "market": "Will England win the 2026 FIFA World Cup?",
          "signal": "SKIP",
          "avg_price": 0.7849,
          "cur_price": 0.2145,
          "usdc_size": 700.45,
          "outcome": "No"
        },
        {
          "market": "Will Spain win the 2026 FIFA World Cup?",
          "signal": "SKIP",
          "avg_price": 0.797,
          "cur_price": 0.2045,
          "usdc_size": 698.68,
          "outcome": "No"
        },
        {
          "market": "Will Argentina win the 2026 FIFA World Cup?",
          "signal": "SKIP",
          "avg_price": 0.8179,
          "cur_price": 0.1825,
          "usdc_size": 699.58,
          "outcome": "No"
        }
      ]
    },
    {
      "wallet": "0xfc230c17ba56862ba0930fa969c359f17886dbe6",
      "name": "h2ck3r",
      "score": 39.2,
      "roi_score": 28.6,
      "calibration_score": 50.0,
      "consistency_score": 50.0,
      "early_entry_score": 0.0,
      "volume_score": 81.3,
      "roi": -7.1,
      "cash_pnl": -471.04,
      "realized_pnl": 1496.98,
      "total_usdc": 43156.8,
      "trade_count": 500,
      "market_count": 14,
      "position_count": 48,
      "resolved_count": 0,
      "win_rate": 0,
      "z_score": 0.0,
      "last_active": "2026-07-12T19:19:43+00:00",
      "top_markets": [
        "Will France win the 2026 FIFA World Cup?",
        "Will Portugal win the 2026 FIFA World Cup?",
        "Will Argentina win the 2026 FIFA World Cup?"
      ],
      "signals": [
        {
          "market": "Will Argentina win the 2026 FIFA World Cup?",
          "signal": "ENTER",
          "avg_price": 0.1801,
          "cur_price": 0.1825,
          "usdc_size": 2920.0,
          "outcome": "Yes"
        },
        {
          "market": "Will Spain win the 2026 FIFA World Cup?",
          "signal": "LATE",
          "avg_price": 0.1912,
          "cur_price": 0.2045,
          "usdc_size": 817.6,
          "outcome": "Yes"
        },
        {
          "market": "Will England win the 2026 FIFA World Cup?",
          "signal": "SKIP",
          "avg_price": 0.1589,
          "cur_price": 0.2145,
          "usdc_size": 858.0,
          "outcome": "Yes"
        },
        {
          "market": "Will France win the 2026 FIFA World Cup?",
          "signal": "SKIP",
          "avg_price": 0.3608,
          "cur_price": 0.3885,
          "usdc_size": 1553.95,
          "outcome": "Yes"
        }
      ]
    },
    {
      "wallet": "0xef94696817d93f66d0e86a4f85b4a5703edef8c4",
      "name": "jimmyjpeg",
      "score": 38.9,
      "roi_score": 24.5,
      "calibration_score": 50.0,
      "consistency_score": 50.0,
      "early_entry_score": 0.0,
      "volume_score": 90.7,
      "roi": -13.3,
      "cash_pnl": -4750.44,
      "realized_pnl": 11421.3,
      "total_usdc": 147267.85,
      "trade_count": 500,
      "market_count": 34,
      "position_count": 11,
      "resolved_count": 0,
      "win_rate": 0,
      "z_score": 0.0,
      "last_active": "2026-07-12T17:50:46+00:00",
      "top_markets": [
        "Will France win the 2026 FIFA World Cup?",
        "Switzerland vs. Colombia: Team to Advance",
        "Will Norway win the 2026 FIFA World Cup?"
      ],
      "signals": [
        {
          "market": "Will France win the 2026 FIFA World Cup?",
          "signal": "ENTER",
          "avg_price": 0.3863,
          "cur_price": 0.3885,
          "usdc_size": 4111.37,
          "outcome": "Yes"
        },
        {
          "market": "Will England win the 2026 FIFA World Cup?",
          "signal": "SKIP",
          "avg_price": 0.8367,
          "cur_price": 0.2145,
          "usdc_size": 17515.9,
          "outcome": "No"
        },
        {
          "market": "Will Spain win the 2026 FIFA World Cup?",
          "signal": "SKIP",
          "avg_price": 0.1402,
          "cur_price": 0.2045,
          "usdc_size": 2675.78,
          "outcome": "Yes"
        }
      ]
    },
    {
      "wallet": "0xa7fb95a2dc1038eac7172b0956fb76481c5d8fde",
      "name": "Traif",
      "score": 38.6,
      "roi_score": 26.5,
      "calibration_score": 50.0,
      "consistency_score": 50.0,
      "early_entry_score": 0.0,
      "volume_score": 81.8,
      "roi": -10.2,
      "cash_pnl": -147.26,
      "realized_pnl": -1.22,
      "total_usdc": 46064.91,
      "trade_count": 500,
      "market_count": 117,
      "position_count": 24,
      "resolved_count": 0,
      "win_rate": 0,
      "z_score": 0.0,
      "last_active": "2026-07-12T21:08:07+00:00",
      "top_markets": [
        "Will WTI Crude Oil (WTI) hit (HIGH) $140 in May?",
        "Will WTI Crude Oil (WTI) hit (HIGH) $115 in May?",
        "Will Civil Contract win the most seats in the 2026 Armenian National Assembly election?"
      ],
      "signals": [
        {
          "market": "Will Argentina win the 2026 FIFA World Cup?",
          "signal": "SKIP",
          "avg_price": 0.8179,
          "cur_price": 0.1825,
          "usdc_size": 1290.05,
          "outcome": "No"
        }
      ]
    },
    {
      "wallet": "0xaaddfa107f870155547ed77d11b540b70dc2d3f1",
      "name": "yxj425",
      "score": 38.4,
      "roi_score": 21.6,
      "calibration_score": 50.0,
      "consistency_score": 50.0,
      "early_entry_score": 0.0,
      "volume_score": 94.1,
      "roi": -17.6,
      "cash_pnl": -869.72,
      "realized_pnl": 0.0,
      "total_usdc": 230881.83,
      "trade_count": 500,
      "market_count": 18,
      "position_count": 4,
      "resolved_count": 0,
      "win_rate": 0,
      "z_score": 0.0,
      "last_active": "2026-07-12T19:20:17+00:00",
      "top_markets": [
        "Will WTI Crude Oil (WTI) hit (HIGH) $120 in May?",
        "Will WTI Crude Oil (WTI) hit (HIGH) $110 in May?",
        "Will Bitcoin reach $85,000 in May?"
      ],
      "signals": [
        {
          "market": "Will France win the 2026 FIFA World Cup?",
          "signal": "SKIP",
          "avg_price": 0.612,
          "cur_price": 0.3885,
          "usdc_size": 1791.69,
          "outcome": "No"
        },
        {
          "market": "Will Argentina win the 2026 FIFA World Cup?",
          "signal": "SKIP",
          "avg_price": 0.8139,
          "cur_price": 0.1825,
          "usdc_size": 2289.0,
          "outcome": "No"
        }
      ]
    },
    {
      "wallet": "0x595029369fbff62529e0a2dfc3f253c0f4a50d33",
      "name": "AhcuraMazda",
      "score": 37.6,
      "roi_score": 20.4,
      "calibration_score": 50.0,
      "consistency_score": 50.0,
      "early_entry_score": 0.0,
      "volume_score": 89.9,
      "roi": -19.4,
      "cash_pnl": -2330.27,
      "realized_pnl": 1580.93,
      "total_usdc": 132247.55,
      "trade_count": 500,
      "market_count": 6,
      "position_count": 4,
      "resolved_count": 0,
      "win_rate": 0,
      "z_score": 0.0,
      "last_active": "2026-07-12T18:26:56+00:00",
      "top_markets": [
        "Will Spain win the 2026 FIFA World Cup?",
        "Will Argentina win the 2026 FIFA World Cup?",
        "Will Portugal win the 2026 FIFA World Cup?"
      ],
      "signals": [
        {
          "market": "Will Argentina win the 2026 FIFA World Cup?",
          "signal": "ENTER",
          "avg_price": 0.1859,
          "cur_price": 0.1825,
          "usdc_size": 8733.95,
          "outcome": "Yes"
        }
      ]
    },
    {
      "wallet": "0xda0f4e3f79a50b8601b3cb9d421f48ce11bbf0e7",
      "name": "Xplayer",
      "score": 35.7,
      "roi_score": 17.4,
      "calibration_score": 50.0,
      "consistency_score": 50.0,
      "early_entry_score": 0.0,
      "volume_score": 79.5,
      "roi": -23.9,
      "cash_pnl": -3389.15,
      "realized_pnl": 1184.56,
      "total_usdc": 34009.79,
      "trade_count": 500,
      "market_count": 3,
      "position_count": 20,
      "resolved_count": 0,
      "win_rate": 0,
      "z_score": 0.0,
      "last_active": "2026-07-12T19:11:56+00:00",
      "top_markets": [
        "Will France win the 2026 FIFA World Cup?",
        "Will Argentina win the 2026 FIFA World Cup?",
        "Will England win the 2026 FIFA World Cup?"
      ],
      "signals": [
        {
          "market": "Will England win the 2026 FIFA World Cup?",
          "signal": "ENTER",
          "avg_price": 0.2129,
          "cur_price": 0.2145,
          "usdc_size": 3472.34,
          "outcome": "Yes"
        },
        {
          "market": "Will Argentina win the 2026 FIFA World Cup?",
          "signal": "LATE",
          "avg_price": 0.1912,
          "cur_price": 0.1825,
          "usdc_size": 7300.0,
          "outcome": "Yes"
        }
      ]
    },
    {
      "wallet": "0xe5241830e8876c115d7dc8311ad9f43d85fdd34f",
      "name": "Sportbetting76",
      "score": 34.0,
      "roi_score": 7.1,
      "calibration_score": 50.0,
      "consistency_score": 50.0,
      "early_entry_score": 0.0,
      "volume_score": 94.2,
      "roi": -39.4,
      "cash_pnl": -96386.6,
      "realized_pnl": 4865.67,
      "total_usdc": 233889.95,
      "trade_count": 500,
      "market_count": 27,
      "position_count": 44,
      "resolved_count": 0,
      "win_rate": 0,
      "z_score": 0.0,
      "last_active": "2026-07-12T20:37:20+00:00",
      "top_markets": [
        "Breel Embolo: 1+ goals",
        "Argentina vs. Switzerland: O/U 9.5 Total Corners",
        "Norway vs. England: Team to Advance"
      ],
      "signals": [
        {
          "market": "Will England win the 2026 FIFA World Cup?",
          "signal": "SKIP",
          "avg_price": 0.0919,
          "cur_price": 0.2145,
          "usdc_size": 39153.95,
          "outcome": "Yes"
        },
        {
          "market": "Will Spain win the 2026 FIFA World Cup?",
          "signal": "SKIP",
          "avg_price": 0.1464,
          "cur_price": 0.2045,
          "usdc_size": 35940.26,
          "outcome": "Yes"
        },
        {
          "market": "Will Argentina win the 2026 FIFA World Cup?",
          "signal": "SKIP",
          "avg_price": 0.798,
          "cur_price": 0.1825,
          "usdc_size": 43961.17,
          "outcome": "No"
        },
        {
          "market": "Will France win the 2026 FIFA World Cup?",
          "signal": "SKIP",
          "avg_price": 0.3279,
          "cur_price": 0.3885,
          "usdc_size": 8740.84,
          "outcome": "Yes"
        }
      ]
    },
    {
      "wallet": "0xdf31f30184b4c19d755257cdee2f7bbb3533d532",
      "name": "0xdF31f30184b4C19d755257CDEe2f7BBb3533d532-1767799465775",
      "score": 33.1,
      "roi_score": 4.8,
      "calibration_score": 50.0,
      "consistency_score": 50.0,
      "early_entry_score": 0.0,
      "volume_score": 91.6,
      "roi": -42.8,
      "cash_pnl": -3012.4,
      "realized_pnl": 13761.07,
      "total_usdc": 165956.42,
      "trade_count": 173,
      "market_count": 17,
      "position_count": 6,
      "resolved_count": 0,
      "win_rate": 0,
      "z_score": 0.0,
      "last_active": "2026-07-12T17:08:20+00:00",
      "top_markets": [
        "Will the Iranian regime fall by March 31?",
        "Will France win the 2026 FIFA World Cup?",
        "Will Argentina win the 2026 FIFA World Cup?"
      ],
      "signals": [
        {
          "market": "Will France win the 2026 FIFA World Cup?",
          "signal": "SKIP",
          "avg_price": 0.3052,
          "cur_price": 0.3885,
          "usdc_size": 4022.18,
          "outcome": "Yes"
        }
      ]
    },
    {
      "wallet": "0x1610db79f753a80207e1d66716be9e91e627ae49",
      "name": "0x1610DB79f753a80207E1d66716be9E91E627AE49-1778875286261",
      "score": 32.5,
      "roi_score": 0.0,
      "calibration_score": 50.0,
      "consistency_score": 50.0,
      "early_entry_score": 0.0,
      "volume_score": 100.0,
      "roi": -71.4,
      "cash_pnl": -127897.53,
      "realized_pnl": -28689.87,
      "total_usdc": 664702.95,
      "trade_count": 500,
      "market_count": 14,
      "position_count": 22,
      "resolved_count": 0,
      "win_rate": 0,
      "z_score": 0.0,
      "last_active": "2026-07-12T19:44:28+00:00",
      "top_markets": [
        "LoL: Bilibili Gaming vs Hanwha Life Esports (BO5) - Mid-Season Invitational Playoffs",
        "LoL: Bilibili Gaming vs Hanwha Life Esports - Game 3 Winner",
        "LoL: Hanwha Life Esports vs LYON (BO5) - Mid-Season Invitational Playoffs"
      ],
      "signals": [
        {
          "market": "Will Argentina win the 2026 FIFA World Cup?",
          "signal": "ENTER",
          "avg_price": 0.1853,
          "cur_price": 0.1825,
          "usdc_size": 26029.17,
          "outcome": "Yes"
        },
        {
          "market": "Will Spain win the 2026 FIFA World Cup?",
          "signal": "SKIP",
          "avg_price": 0.1904,
          "cur_price": 0.2045,
          "usdc_size": 25209.94,
          "outcome": "Yes"
        }
      ]
    },
    {
      "wallet": "0x1e3f673cbd329df727d564e07e9f9dfcd40ae00b",
      "name": "pmic3",
      "score": 32.5,
      "roi_score": 6.3,
      "calibration_score": 50.0,
      "consistency_score": 50.0,
      "early_entry_score": 0.0,
      "volume_score": 81.1,
      "roi": -40.5,
      "cash_pnl": -3518.64,
      "realized_pnl": 254.32,
      "total_usdc": 41714.43,
      "trade_count": 500,
      "market_count": 17,
      "position_count": 21,
      "resolved_count": 0,
      "win_rate": 0,
      "z_score": 0.0,
      "last_active": "2026-07-12T22:03:20+00:00",
      "top_markets": [
        "Will Norway vs. England end in a draw?",
        "Will Kylian Mbappe be the top goalscorer at the 2026 FIFA World Cup?",
        "Will England reach the Semifinals at the 2026 FIFA World Cup?"
      ],
      "signals": []
    },
    {
      "wallet": "0x054790303ef27c09351c6ee72fdbb3b83e0d9926",
      "name": "rchiang",
      "score": 31.9,
      "roi_score": 0.0,
      "calibration_score": 50.0,
      "consistency_score": 50.0,
      "early_entry_score": 0.0,
      "volume_score": 94.3,
      "roi": -67.9,
      "cash_pnl": -6572.24,
      "realized_pnl": -1384.89,
      "total_usdc": 236513.55,
      "trade_count": 500,
      "market_count": 317,
      "position_count": 15,
      "resolved_count": 0,
      "win_rate": 0,
      "z_score": 0.0,
      "last_active": "2026-07-12T20:41:52+00:00",
      "top_markets": [
        "Kraken IPO by March 31, 2026?",
        "Spread: United States (-1.5)",
        "Kraken IPO by December 31, 2026?"
      ],
      "signals": [
        {
          "market": "Will France win the 2026 FIFA World Cup?",
          "signal": "SKIP",
          "avg_price": 0.1709,
          "cur_price": 0.3885,
          "usdc_size": 2453.81,
          "outcome": "Yes"
        }
      ]
    },
    {
      "wallet": "0xc781e8dd03946230f2f32ab36077998bcb4a59d7",
      "name": "Alphax",
      "score": 31.7,
      "roi_score": 0.0,
      "calibration_score": 50.0,
      "consistency_score": 50.0,
      "early_entry_score": 0.0,
      "volume_score": 91.6,
      "roi": -92.7,
      "cash_pnl": -169667.08,
      "realized_pnl": 1137.39,
      "total_usdc": 165432.63,
      "trade_count": 500,
      "market_count": 49,
      "position_count": 22,
      "resolved_count": 0,
      "win_rate": 0,
      "z_score": 0.0,
      "last_active": "2026-07-12T22:41:43+00:00",
      "top_markets": [
        "Will Argentina win the 2026 FIFA World Cup?",
        "Will Ronaldo Cry at the World Cup?",
        "Will Spain win the 2026 FIFA World Cup?"
      ],
      "signals": [
        {
          "market": "Will France win the 2026 FIFA World Cup?",
          "signal": "SKIP",
          "avg_price": 0.2805,
          "cur_price": 0.3885,
          "usdc_size": 3973.35,
          "outcome": "Yes"
        }
      ]
    },
    {
      "wallet": "0x032eb1bc893940263ad0b01889f262fc232f2a9e",
      "name": "purplegatto",
      "score": 31.5,
      "roi_score": 0.0,
      "calibration_score": 50.0,
      "consistency_score": 50.0,
      "early_entry_score": 0.0,
      "volume_score": 89.6,
      "roi": -98.4,
      "cash_pnl": -2784778.95,
      "realized_pnl": 7767.89,
      "total_usdc": 127386.72,
      "trade_count": 500,
      "market_count": 40,
      "position_count": 500,
      "resolved_count": 0,
      "win_rate": 0,
      "z_score": 0.0,
      "last_active": "2026-07-12T22:45:25+00:00",
      "top_markets": [
        "Argentina vs. Switzerland: Team to Advance",
        "Argentina to win the second half?",
        "Will Spain win the 2026 FIFA World Cup?"
      ],
      "signals": [
        {
          "market": "Will Argentina win the 2026 FIFA World Cup?",
          "signal": "LATE",
          "avg_price": 0.1754,
          "cur_price": 0.1825,
          "usdc_size": 1978.46,
          "outcome": "Yes"
        },
        {
          "market": "Will England win the 2026 FIFA World Cup?",
          "signal": "SKIP",
          "avg_price": 0.1494,
          "cur_price": 0.2145,
          "usdc_size": 10286.01,
          "outcome": "Yes"
        },
        {
          "market": "Will Argentina win the 2026 FIFA World Cup?",
          "signal": "SKIP",
          "avg_price": 0.8148,
          "cur_price": 0.1825,
          "usdc_size": 18790.1,
          "outcome": "No"
        },
        {
          "market": "Will France win the 2026 FIFA World Cup?",
          "signal": "SKIP",
          "avg_price": 0.2672,
          "cur_price": 0.3885,
          "usdc_size": 2433.56,
          "outcome": "Yes"
        },
        {
          "market": "Will Spain win the 2026 FIFA World Cup?",
          "signal": "SKIP",
          "avg_price": 0.8045,
          "cur_price": 0.2045,
          "usdc_size": 3964.11,
          "outcome": "No"
        }
      ]
    },
    {
      "wallet": "0xc6325d53416cfe31c8becc1919e3c73b4c456871",
      "name": "ssalu",
      "score": 31.5,
      "roi_score": 0.0,
      "calibration_score": 50.0,
      "consistency_score": 50.0,
      "early_entry_score": 0.0,
      "volume_score": 90.0,
      "roi": -100.0,
      "cash_pnl": -18586.93,
      "realized_pnl": 0.0,
      "total_usdc": 135014.72,
      "trade_count": 389,
      "market_count": 275,
      "position_count": 58,
      "resolved_count": 0,
      "win_rate": 0,
      "z_score": 0.0,
      "last_active": "2026-07-12T18:27:04+00:00",
      "top_markets": [
        "Exact Score: Any Other Score?",
        "Bitcoin Up or Down - May 26, 2:00PM-2:05PM ET",
        "Will France win the 2026 FIFA World Cup?"
      ],
      "signals": []
    },
    {
      "wallet": "0x7967ded7c72e2fa03d732f5a5e21667f1741f4a0",
      "name": "djdjdj",
      "score": 31.3,
      "roi_score": 0.0,
      "calibration_score": 50.0,
      "consistency_score": 50.0,
      "early_entry_score": 0.0,
      "volume_score": 88.4,
      "roi": -98.6,
      "cash_pnl": -177386.54,
      "realized_pnl": -2146.35,
      "total_usdc": 108946.37,
      "trade_count": 500,
      "market_count": 137,
      "position_count": 184,
      "resolved_count": 0,
      "win_rate": 0,
      "z_score": 0.0,
      "last_active": "2026-07-12T19:44:14+00:00",
      "top_markets": [
        "Bitcoin Up or Down - December 21, 11:15AM-11:30AM ET",
        "Exact Score: England 1 - 0 Ghana?",
        "Bitcoin Up or Down - December 21, 9:45PM-10:00PM ET"
      ],
      "signals": []
    },
    {
      "wallet": "0x16dd1fa438500c3603a68004438a349cde43adf5",
      "name": "Guest288228",
      "score": 30.8,
      "roi_score": 0.0,
      "calibration_score": 50.0,
      "consistency_score": 50.0,
      "early_entry_score": 0.0,
      "volume_score": 83.4,
      "roi": -56.6,
      "cash_pnl": -177.32,
      "realized_pnl": 214.46,
      "total_usdc": 56947.36,
      "trade_count": 500,
      "market_count": 15,
      "position_count": 40,
      "resolved_count": 0,
      "win_rate": 0,
      "z_score": 0.0,
      "last_active": "2026-07-12T22:35:16+00:00",
      "top_markets": [
        "Will England win the 2026 FIFA World Cup?",
        "Will France win the 2026 FIFA World Cup?",
        "Will Norway win the 2026 FIFA World Cup?"
      ],
      "signals": []
    },
    {
      "wallet": "0xcfe0c7ac8f82b61d6284d46c8720ad9471ca507c",
      "name": "RKSLastHope",
      "score": 30.5,
      "roi_score": 0.0,
      "calibration_score": 50.0,
      "consistency_score": 50.0,
      "early_entry_score": 0.0,
      "volume_score": 80.2,
      "roi": -100.0,
      "cash_pnl": -1022.07,
      "realized_pnl": -1.32,
      "total_usdc": 37024.63,
      "trade_count": 500,
      "market_count": 181,
      "position_count": 4,
      "resolved_count": 0,
      "win_rate": 0,
      "z_score": 0.0,
      "last_active": "2026-07-12T18:51:17+00:00",
      "top_markets": [
        "Bitcoin Up or Down - May 19, 2:20PM-2:25PM ET",
        "Bitcoin Up or Down - July 3, 3:00PM-3:05PM ET",
        "Will Spain win the 2026 FIFA World Cup?"
      ],
      "signals": []
    },
    {
      "wallet": "0xba004db22eb6871b051f1dbc8be443275d4b7a0e",
      "name": "baton1401",
      "score": 30.4,
      "roi_score": 0.0,
      "calibration_score": 50.0,
      "consistency_score": 50.0,
      "early_entry_score": 0.0,
      "volume_score": 79.0,
      "roi": -91.9,
      "cash_pnl": -2195.28,
      "realized_pnl": 2229.15,
      "total_usdc": 31811.25,
      "trade_count": 288,
      "market_count": 40,
      "position_count": 7,
      "resolved_count": 0,
      "win_rate": 0,
      "z_score": 0.0,
      "last_active": "2026-07-12T17:55:43+00:00",
      "top_markets": [
        "Will France win the 2026 FIFA World Cup?",
        "Will Russia capture Kostyantynivka by June 30?",
        "Will Trump visit China by March 31?"
      ],
      "signals": []
    },
    {
      "wallet": "0xc9ded4d5f6eec0a75907ebb924c164a4aea381d9",
      "name": "LMVM",
      "score": 30.4,
      "roi_score": 0.0,
      "calibration_score": 50.0,
      "consistency_score": 50.0,
      "early_entry_score": 0.0,
      "volume_score": 79.4,
      "roi": -100.0,
      "cash_pnl": -656.49,
      "realized_pnl": -24.75,
      "total_usdc": 33294.97,
      "trade_count": 500,
      "market_count": 35,
      "position_count": 35,
      "resolved_count": 0,
      "win_rate": 0,
      "z_score": 0.0,
      "last_active": "2026-07-12T17:42:23+00:00",
      "top_markets": [
        "Will the lowest temperature in Miami be between 82-83\u00b0F on July 9?",
        "Will the lowest temperature in Paris be 21\u00b0C on July 10?",
        "Will the lowest temperature in New York City be between 72-73\u00b0F on July 9?"
      ],
      "signals": []
    },
    {
      "wallet": "0xce919ef05d417e5b288207e318e6673fd3a49c9f",
      "name": "johnnyutah",
      "score": 30.3,
      "roi_score": 0.0,
      "calibration_score": 50.0,
      "consistency_score": 50.0,
      "early_entry_score": 0.0,
      "volume_score": 77.6,
      "roi": -100.0,
      "cash_pnl": -6182.42,
      "realized_pnl": -63.63,
      "total_usdc": 26557.39,
      "trade_count": 136,
      "market_count": 71,
      "position_count": 38,
      "resolved_count": 0,
      "win_rate": 0,
      "z_score": 0.0,
      "last_active": "2026-07-12T19:29:23+00:00",
      "top_markets": [
        "Washington vs. Wisconsin Badgers",
        "BYU vs. Texas Tech Red Raiders",
        "Georgia Tech vs. Boston College"
      ],
      "signals": []
    },
    {
      "wallet": "0x21064fd320bfd5a86f8c92a94d3209edf4154dea",
      "name": "rainbowlilies",
      "score": 29.6,
      "roi_score": 0.0,
      "calibration_score": 50.0,
      "consistency_score": 50.0,
      "early_entry_score": 0.0,
      "volume_score": 71.3,
      "roi": -50.2,
      "cash_pnl": -53658.3,
      "realized_pnl": -74335.93,
      "total_usdc": 11538.38,
      "trade_count": 500,
      "market_count": 71,
      "position_count": 500,
      "resolved_count": 0,
      "win_rate": 0,
      "z_score": 0.0,
      "last_active": "2026-07-12T22:44:55+00:00",
      "top_markets": [
        "Will Manuel Bompard win the 2027 French presidential election?",
        "Will Xavier Bertrand win the 2027 French presidential election?",
        "Will Mathilde Panot win the 2027 French presidential election?"
      ],
      "signals": [
        {
          "market": "Will Spain win the 2026 FIFA World Cup?",
          "signal": "ENTER",
          "avg_price": 0.205,
          "cur_price": 0.2045,
          "usdc_size": 3066.01,
          "outcome": "Yes"
        },
        {
          "market": "Will France win the 2026 FIFA World Cup?",
          "signal": "ENTER",
          "avg_price": 0.3815,
          "cur_price": 0.3885,
          "usdc_size": 2331.03,
          "outcome": "Yes"
        },
        {
          "market": "Will Argentina win the 2026 FIFA World Cup?",
          "signal": "LATE",
          "avg_price": 0.1884,
          "cur_price": 0.1825,
          "usdc_size": 7363.47,
          "outcome": "Yes"
        },
        {
          "market": "Will England win the 2026 FIFA World Cup?",
          "signal": "SKIP",
          "avg_price": 0.7853,
          "cur_price": 0.2145,
          "usdc_size": 1716.51,
          "outcome": "No"
        },
        {
          "market": "Will France win on 2026-07-14?",
          "signal": "SKIP",
          "avg_price": 0.3333,
          "cur_price": 0.415,
          "usdc_size": 830.0,
          "outcome": "Yes"
        }
      ]
    },
    {
      "wallet": "0xc8588c8b10c8dff50635baf8bf4071a0bdcfba6e",
      "name": "camels",
      "score": 29.2,
      "roi_score": 0.0,
      "calibration_score": 50.0,
      "consistency_score": 50.0,
      "early_entry_score": 0.0,
      "volume_score": 66.5,
      "roi": -91.0,
      "cash_pnl": -986.49,
      "realized_pnl": 642.1,
      "total_usdc": 6172.94,
      "trade_count": 87,
      "market_count": 45,
      "position_count": 21,
      "resolved_count": 0,
      "win_rate": 0,
      "z_score": 0.0,
      "last_active": "2026-07-12T19:12:47+00:00",
      "top_markets": [
        "Will T\u00fcrkiye win Group D in the 2026 FIFA World Cup?",
        "Will France win the 2026 FIFA World Cup?",
        "Will Spain win the 2026 FIFA World Cup?"
      ],
      "signals": []
    },
    {
      "wallet": "0xb5a8181310a2b1b8c4c67a631a13aa1812b15e97",
      "name": "0xb5A8181310A2B1B8C4C67a631a13Aa1812b15E97-1769943827971",
      "score": 29.0,
      "roi_score": 0.9,
      "calibration_score": 50.0,
      "consistency_score": 50.0,
      "early_entry_score": 0.0,
      "volume_score": 62.0,
      "roi": -48.6,
      "cash_pnl": -564.42,
      "realized_pnl": 1.22,
      "total_usdc": 3396.73,
      "trade_count": 199,
      "market_count": 70,
      "position_count": 38,
      "resolved_count": 0,
      "win_rate": 0,
      "z_score": 0.0,
      "last_active": "2026-07-12T20:20:35+00:00",
      "top_markets": [
        "Bitcoin Up or Down - February 7, 5:15PM-5:30PM ET",
        "Bitcoin Up or Down - February 7, 5:00PM-5:15PM ET",
        "Bitcoin Up or Down - March 12, 8:45AM-9:00AM ET"
      ],
      "signals": [
        {
          "market": "Will Argentina win the 2026 FIFA World Cup?",
          "signal": "ENTER",
          "avg_price": 0.1839,
          "cur_price": 0.1825,
          "usdc_size": 596.81,
          "outcome": "Yes"
        }
      ]
    },
    {
      "wallet": "0xda469be83a18765bc0ce9de2889f850ea6cb5436",
      "name": "TherealG-994",
      "score": 28.9,
      "roi_score": 0.0,
      "calibration_score": 50.0,
      "consistency_score": 50.0,
      "early_entry_score": 0.0,
      "volume_score": 64.4,
      "roi": -100.0,
      "cash_pnl": -47.91,
      "realized_pnl": 0.0,
      "total_usdc": 4687.86,
      "trade_count": 31,
      "market_count": 20,
      "position_count": 6,
      "resolved_count": 0,
      "win_rate": 0,
      "z_score": 0.0,
      "last_active": "2026-07-12T19:32:23+00:00",
      "top_markets": [
        "Will Argentina win the 2026 FIFA World Cup?",
        "Will Spain win the 2026 FIFA World Cup?",
        "Will France win the 2026 FIFA World Cup?"
      ],
      "signals": []
    }
  ],
  "markets": [
    {
      "id": "0x0c4cd2055d6ea89354ffddc55d6dbcef9355748112ea952fc925f3db6a5c457f",
      "question": "Will Argentina win the 2026 FIFA World Cup?",
      "volume": "131715276.4376393",
      "liquidity": "7694782.90196",
      "end_date": "2026-07-20T00:00:00Z"
    },
    {
      "id": "0xecba7b1db1c698ab73b3572abfcde327a02b5112676144e049edcc1e1e0f5b0b",
      "question": "France vs. Spain: Team to Advance",
      "volume": "3689342.2839878835",
      "liquidity": "3350552.6708",
      "end_date": "2026-07-14T19:00:00Z"
    },
    {
      "id": "0x375409bc5eeeff961e82b479caeccc20f33d15738e5bce1186d628aa3d9dfb1f",
      "question": "Will England win the 2026 FIFA World Cup?",
      "volume": "98355186.05625406",
      "liquidity": "7264344.76264",
      "end_date": "2026-07-20T00:00:00Z"
    },
    {
      "id": "0x9b6fef249040fd17e9c107955b37ac2c3e923509b6b0ff01cc463a331ddeb894",
      "question": "Will France win the 2026 FIFA World Cup?",
      "volume": "114946655.96684961",
      "liquidity": "6629491.97316",
      "end_date": "2026-07-20T00:00:00Z"
    },
    {
      "id": "0x7976b8dbacf9077eb1453a62bcefd6ab2df199acd28aad276ff0d920d6992892",
      "question": "Will Spain win the 2026 FIFA World Cup?",
      "volume": "106479235.71174508",
      "liquidity": "7838477.92775",
      "end_date": "2026-07-20T00:00:00Z"
    },
    {
      "id": "0xaa53ce562be767321e2f0cba9f7b3207fde7d2204dbb7f9b5d804996eba7de7c",
      "question": "Will Mostafa Pourmohammadi be head of state in Iran end of 2026?",
      "volume": "3315112.226454994",
      "liquidity": "50648.27929",
      "end_date": "2026-12-31T00:00:00Z"
    },
    {
      "id": "0x20fac1c925b7a2fed6b3b2736f47a800b4d0d4001b9deaeb7b918868eb63d081",
      "question": "Will France win on 2026-07-14?",
      "volume": "2509711.7411879636",
      "liquidity": "3638048.032",
      "end_date": "2026-07-14T19:00:00Z"
    },
    {
      "id": "0xfb2314dcad9273745bd3de0db31a2036cda3eae847039a58e41a3c2dcc233657",
      "question": "France vs. Spain: O/U 2.5",
      "volume": "701543.7841480003",
      "liquidity": "1900793.7451",
      "end_date": "2026-07-14T19:00:00Z"
    },
    {
      "id": "0x4558afc5dfac49c7b2e3ea7c088930c5ae4811ae374698327be422f1f16daea2",
      "question": "Arizona Diamondbacks vs. Los Angeles Dodgers",
      "volume": "692060.9867070002",
      "liquidity": "148556.0304",
      "end_date": "2026-07-19T20:10:00Z"
    },
    {
      "id": "0xafb4cbefe1c36ccce9665d21c9093e94d6122f16c39b71c0aa383670f25aa956",
      "question": "Toronto Blue Jays vs. San Diego Padres",
      "volume": "615539.0236510014",
      "liquidity": "115964.3243",
      "end_date": "2026-07-19T20:10:00Z"
    },
    {
      "id": "0x3b9204e0fcba9234e3eaca1a941a342e4ce82aeb4ba373c668f2e8a72f1d41de",
      "question": "Will France vs. Spain end in a draw?",
      "volume": "618767.8357349989",
      "liquidity": "2971520.0287",
      "end_date": "2026-07-14T19:00:00Z"
    },
    {
      "id": "0x73d9b98f619d738cca001cfde25654d409a132f0eb565ae98972b62b123a4da0",
      "question": "Will Ali Motahari be head of state in Iran end of 2026?",
      "volume": "804180.2856059988",
      "liquidity": "53745.94303",
      "end_date": "2026-12-31T00:00:00Z"
    },
    {
      "id": "0xa90673a1fa1316d0d0ac76e02357c4901527cf294cd0250c1effae572bd43a2c",
      "question": "Colorado Rockies vs. San Francisco Giants",
      "volume": "531391.2296510014",
      "liquidity": "434120.9327",
      "end_date": "2026-07-19T20:05:00Z"
    },
    {
      "id": "0xcacd424332319971356c757c025b45a4eb5643b919fb3bd2f84051afea599b13",
      "question": "Strait of Hormuz traffic returns to normal by July 15?",
      "volume": "9419140.488336962",
      "liquidity": "611815.19589",
      "end_date": "2026-07-15T00:00:00Z"
    },
    {
      "id": "0xf656cf9c2390d92527023b97273f8a3279a751135d28f157fe8ad98e856f3f50",
      "question": "Exact Score: France 2 - 1 Spain?",
      "volume": "408167.2829060008",
      "liquidity": "2183430.0722",
      "end_date": "2026-07-14T19:00:00Z"
    },
    {
      "id": "0xb8e6d129a06d0ccb21d7b32eb529ea455eddba3cf29bfa097112202cbdf5bf21",
      "question": "Strait of Hormuz traffic returns to normal by July 31?",
      "volume": "15689353.234208291",
      "liquidity": "977229.342",
      "end_date": "2026-07-31T00:00:00Z"
    },
    {
      "id": "0x6c486242e79252cc0bb57163a3b8d95e3b9538ea6a1de2e91848beeb5c6ad986",
      "question": "Iran full airspace closure by July 15?",
      "volume": "2153132.249753004",
      "liquidity": "45699.15111",
      "end_date": "2026-07-15T23:59:00Z"
    },
    {
      "id": "0xe6ef89a8799219484b35f1a361873d167ccbdea0cda608fdfa2d4073e8e1e22e",
      "question": "France vs. Spain: Both Teams to Score",
      "volume": "356308.80557600036",
      "liquidity": "413021.8223",
      "end_date": "2026-07-14T19:00:00Z"
    },
    {
      "id": "0x5db999fad322cea2914535aae5517060c3f80ad6d8c0231cde2124a434d16846",
      "question": "Will the U.S. invade Iran before 2027?",
      "volume": "40788160.540636145",
      "liquidity": "453661.5986",
      "end_date": "2026-12-31T00:00:00Z"
    },
    {
      "id": "0x2a28cc33492516116690a20d290f9922acbe0ed367ff52a6082154474c7f2971",
      "question": "Will the Fed increase interest rates by 50+ bps after the July 2026 meeting?",
      "volume": "9120557.948583893",
      "liquidity": "235509.02252",
      "end_date": "2026-07-29T00:00:00Z"
    }
  ]
}