{
  "last_updated": "2026-07-02T11:07:22.138753+00:00",
  "whale_count": 50,
  "market_count": 20,
  "whales": [
    {
      "wallet": "0xa2cced8bfae7d645f7f437fb76becf2fcbb70cbc",
      "name": "justwins",
      "score": 47.3,
      "roi_score": 51.8,
      "calibration_score": 50.0,
      "consistency_score": 50.0,
      "early_entry_score": 0.0,
      "volume_score": 92.2,
      "roi": 27.8,
      "cash_pnl": 3757.96,
      "realized_pnl": 0.0,
      "total_usdc": 179549.68,
      "trade_count": 500,
      "market_count": 9,
      "position_count": 2,
      "resolved_count": 0,
      "win_rate": 0,
      "z_score": 0.0,
      "last_active": "2026-07-01T19:59:25+00:00",
      "top_markets": [
        "Will Canada win on 2026-06-12?",
        "Spread: Argentina (-1.5)",
        "Will Belgium win the 2026 FIFA World Cup?"
      ],
      "signals": [
        {
          "market": "Will Belgium win the 2026 FIFA World Cup?",
          "signal": "SKIP",
          "avg_price": 0.0121,
          "cur_price": 0.0155,
          "usdc_size": 17293.57,
          "outcome": "Yes"
        }
      ]
    },
    {
      "wallet": "0x189cafec481ed3fec5e4a5ad97ece8af2d0cc9ae",
      "name": "Colocolocampeon",
      "score": 44.7,
      "roi_score": 50.0,
      "calibration_score": 50.0,
      "consistency_score": 50.0,
      "early_entry_score": 0.0,
      "volume_score": 71.7,
      "roi": null,
      "cash_pnl": 0,
      "realized_pnl": 0,
      "total_usdc": 12148.15,
      "trade_count": 80,
      "market_count": 8,
      "position_count": 0,
      "resolved_count": 0,
      "win_rate": 0,
      "z_score": 0.0,
      "last_active": "2026-07-02T02:09:14+00:00",
      "top_markets": [
        "Will Belgium win the 2026 FIFA World Cup?",
        "Scotland vs. Brazil: O/U 9.5 Total Corners",
        "Will Senegal win the 2026 FIFA World Cup?"
      ],
      "signals": []
    },
    {
      "wallet": "0x0ec49699229f8c4bacdb7ae8bc9fd2c0f7c9f4a4",
      "name": "-Motionless-",
      "score": 44.3,
      "roi_score": 42.2,
      "calibration_score": 50.0,
      "consistency_score": 50.0,
      "early_entry_score": 0.0,
      "volume_score": 91.8,
      "roi": 13.3,
      "cash_pnl": 1626.4,
      "realized_pnl": 125.18,
      "total_usdc": 171085.61,
      "trade_count": 500,
      "market_count": 152,
      "position_count": 25,
      "resolved_count": 0,
      "win_rate": 0,
      "z_score": 0.0,
      "last_active": "2026-07-02T10:44:52+00:00",
      "top_markets": [
        "Will Norway win the 2026 FIFA World Cup?",
        "Will Kroger Q1 identical sales without fuel growth be below 1%?",
        "Will Warsh say \"Trend\" during June Press Conference?"
      ],
      "signals": [
        {
          "market": "Will Argentina win the 2026 FIFA World Cup?",
          "signal": "SKIP",
          "avg_price": 0.0879,
          "cur_price": 0.1805,
          "usdc_size": 2051.14,
          "outcome": "Yes"
        },
        {
          "market": "Will England win the 2026 FIFA World Cup?",
          "signal": "SKIP",
          "avg_price": 0.1119,
          "cur_price": 0.0825,
          "usdc_size": 736.61,
          "outcome": "Yes"
        },
        {
          "market": "Will Spain win the 2026 FIFA World Cup?",
          "signal": "SKIP",
          "avg_price": 0.1639,
          "cur_price": 0.1005,
          "usdc_size": 612.8,
          "outcome": "Yes"
        },
        {
          "market": "Will France win the 2026 FIFA World Cup?",
          "signal": "SKIP",
          "avg_price": 0.1709,
          "cur_price": 0.3505,
          "usdc_size": 2049.71,
          "outcome": "Yes"
        }
      ]
    },
    {
      "wallet": "0x2bbd8ee618a9f9f2f1a1385e7f246fa1f2a09cf3",
      "name": "Romelu.Lukaku",
      "score": 43.8,
      "roi_score": 50.0,
      "calibration_score": 50.0,
      "consistency_score": 50.0,
      "early_entry_score": 0.0,
      "volume_score": 62.9,
      "roi": null,
      "cash_pnl": 0,
      "realized_pnl": 0,
      "total_usdc": 3820.18,
      "trade_count": 2,
      "market_count": 1,
      "position_count": 0,
      "resolved_count": 0,
      "win_rate": 0,
      "z_score": 0.0,
      "last_active": "2026-07-01T17:45:34+00:00",
      "top_markets": [
        "Will Belgium win the 2026 FIFA World Cup?"
      ],
      "signals": []
    },
    {
      "wallet": "0x22bf80284f27fcf768d8724ce84b88b575630b46",
      "name": "JeremieDoku",
      "score": 43.8,
      "roi_score": 50.0,
      "calibration_score": 50.0,
      "consistency_score": 50.0,
      "early_entry_score": 0.0,
      "volume_score": 62.9,
      "roi": null,
      "cash_pnl": 0,
      "realized_pnl": 0,
      "total_usdc": 3835.68,
      "trade_count": 2,
      "market_count": 1,
      "position_count": 0,
      "resolved_count": 0,
      "win_rate": 0,
      "z_score": 0.0,
      "last_active": "2026-07-01T17:43:07+00:00",
      "top_markets": [
        "Will Belgium win the 2026 FIFA World Cup?"
      ],
      "signals": []
    },
    {
      "wallet": "0x012117729450d19b22018ad8c6e9357bcd34f722",
      "name": "MenacingTurtle",
      "score": 42.7,
      "roi_score": 37.9,
      "calibration_score": 50.0,
      "consistency_score": 50.0,
      "early_entry_score": 0.0,
      "volume_score": 87.8,
      "roi": 6.9,
      "cash_pnl": 1825.8,
      "realized_pnl": 3813.56,
      "total_usdc": 100490.4,
      "trade_count": 500,
      "market_count": 71,
      "position_count": 66,
      "resolved_count": 0,
      "win_rate": 0,
      "z_score": 0.0,
      "last_active": "2026-07-02T10:52:25+00:00",
      "top_markets": [
        "Will England reach the Quarterfinals at the 2026 FIFA World Cup?",
        "Will Senegal reach the Quarterfinals at the 2026 FIFA World Cup?",
        "Will Belgium reach the Round of 16 at the 2026 FIFA World Cup?"
      ],
      "signals": [
        {
          "market": "Will Belgium win the 2026 FIFA World Cup?",
          "signal": "SKIP",
          "avg_price": 0.0031,
          "cur_price": 0.0155,
          "usdc_size": 2994.52,
          "outcome": "Yes"
        }
      ]
    },
    {
      "wallet": "0x14c32680ffc318892e0d019181e4161aa34cdf68",
      "name": "borntoolate.eth",
      "score": 42.4,
      "roi_score": 35.5,
      "calibration_score": 50.0,
      "consistency_score": 50.0,
      "early_entry_score": 0.0,
      "volume_score": 93.0,
      "roi": 3.2,
      "cash_pnl": 3557.02,
      "realized_pnl": -10959.16,
      "total_usdc": 198497.64,
      "trade_count": 500,
      "market_count": 15,
      "position_count": 10,
      "resolved_count": 0,
      "win_rate": 0,
      "z_score": 0.0,
      "last_active": "2026-07-02T11:06:07+00:00",
      "top_markets": [
        "Will Belgium win on 2026-07-01?",
        "Will France win the 2026 FIFA World Cup?",
        "United States vs. Bosnia and Herzegovina: Team to Advance"
      ],
      "signals": [
        {
          "market": "Will Spain win the 2026 FIFA World Cup?",
          "signal": "ENTER",
          "avg_price": 0.1,
          "cur_price": 0.1005,
          "usdc_size": 893.24,
          "outcome": "Yes"
        },
        {
          "market": "Will USA win the 2026 FIFA World Cup?",
          "signal": "SKIP",
          "avg_price": 0.0308,
          "cur_price": 0.0275,
          "usdc_size": 5700.14,
          "outcome": "Yes"
        },
        {
          "market": "Will France win the 2026 FIFA World Cup?",
          "signal": "SKIP",
          "avg_price": 0.6232,
          "cur_price": 0.3505,
          "usdc_size": 105705.1,
          "outcome": "No"
        },
        {
          "market": "Will Morocco win the 2026 FIFA World Cup?",
          "signal": "SKIP",
          "avg_price": 0.0235,
          "cur_price": 0.0255,
          "usdc_size": 2445.1,
          "outcome": "Yes"
        }
      ]
    },
    {
      "wallet": "0x56acab44cfca2e88bb9b3406890aea7bfa0cd77e",
      "name": "dv-pm",
      "score": 42.3,
      "roi_score": 32.8,
      "calibration_score": 50.0,
      "consistency_score": 50.0,
      "early_entry_score": 0.0,
      "volume_score": 100.0,
      "roi": -0.9,
      "cash_pnl": -1224.94,
      "realized_pnl": -23.51,
      "total_usdc": 1174665.86,
      "trade_count": 500,
      "market_count": 368,
      "position_count": 62,
      "resolved_count": 0,
      "win_rate": 0,
      "z_score": 0.0,
      "last_active": "2026-07-02T10:35:34+00:00",
      "top_markets": [
        "Mexico vs. Ecuador: O/U 7.5 Total Corners",
        "Spread: France (-1.5)",
        "Will Portugal win the 2026 FIFA World Cup?"
      ],
      "signals": [
        {
          "market": "Will Norway win the 2026 FIFA World Cup?",
          "signal": "LATE",
          "avg_price": 0.0208,
          "cur_price": 0.0195,
          "usdc_size": 1397.91,
          "outcome": "Yes"
        },
        {
          "market": "Will Portugal win the 2026 FIFA World Cup?",
          "signal": "LATE",
          "avg_price": 0.0573,
          "cur_price": 0.0605,
          "usdc_size": 3160.29,
          "outcome": "Yes"
        },
        {
          "market": "Will Spain win the 2026 FIFA World Cup?",
          "signal": "SKIP",
          "avg_price": 0.1117,
          "cur_price": 0.1005,
          "usdc_size": 8994.73,
          "outcome": "Yes"
        },
        {
          "market": "Will England win the 2026 FIFA World Cup?",
          "signal": "SKIP",
          "avg_price": 0.107,
          "cur_price": 0.0825,
          "usdc_size": 6827.72,
          "outcome": "Yes"
        }
      ]
    },
    {
      "wallet": "0xe60f07a844bd18448eb3b23818f94bec1589f4b4",
      "name": "cryptoincome",
      "score": 42.3,
      "roi_score": 35.0,
      "calibration_score": 50.0,
      "consistency_score": 50.0,
      "early_entry_score": 0.0,
      "volume_score": 92.6,
      "roi": 2.6,
      "cash_pnl": 2497.24,
      "realized_pnl": 0.0,
      "total_usdc": 188762.13,
      "trade_count": 500,
      "market_count": 280,
      "position_count": 138,
      "resolved_count": 0,
      "win_rate": 0,
      "z_score": 0.0,
      "last_active": "2026-07-01T23:05:32+00:00",
      "top_markets": [
        "Will Germany win on 2026-06-20?",
        "ODI Series India vs Afghanistan: India vs Afghanistan",
        "Will Silver (SI) settle at <$50 in June?"
      ],
      "signals": [
        {
          "market": "Will Argentina win the 2026 FIFA World Cup?",
          "signal": "SKIP",
          "avg_price": 0.885,
          "cur_price": 0.1805,
          "usdc_size": 860.48,
          "outcome": "No"
        },
        {
          "market": "Will England win the 2026 FIFA World Cup?",
          "signal": "SKIP",
          "avg_price": 0.868,
          "cur_price": 0.0825,
          "usdc_size": 811.07,
          "outcome": "No"
        }
      ]
    },
    {
      "wallet": "0x448861155279dbf833d041b963e3ac854599e319",
      "name": "Flipadelphia",
      "score": 42.2,
      "roi_score": 32.4,
      "calibration_score": 50.0,
      "consistency_score": 50.0,
      "early_entry_score": 0.0,
      "volume_score": 100.0,
      "roi": -1.3,
      "cash_pnl": -3679.46,
      "realized_pnl": 119.8,
      "total_usdc": 510744.23,
      "trade_count": 500,
      "market_count": 39,
      "position_count": 15,
      "resolved_count": 0,
      "win_rate": 0,
      "z_score": 0.0,
      "last_active": "2026-07-02T10:47:50+00:00",
      "top_markets": [
        "Will England win the 2026 FIFA World Cup?",
        "Will Keiko Fujimori win the 2026 Peruvian presidential election?",
        "Detroit Tigers vs. New York Yankees"
      ],
      "signals": [
        {
          "market": "Will Norway win the 2026 FIFA World Cup?",
          "signal": "ENTER",
          "avg_price": 0.0191,
          "cur_price": 0.0195,
          "usdc_size": 5850.0,
          "outcome": "Yes"
        },
        {
          "market": "Will Belgium win the 2026 FIFA World Cup?",
          "signal": "SKIP",
          "avg_price": 0.014,
          "cur_price": 0.0155,
          "usdc_size": 15500.0,
          "outcome": "Yes"
        },
        {
          "market": "Will England win the 2026 FIFA World Cup?",
          "signal": "SKIP",
          "avg_price": 0.1059,
          "cur_price": 0.0825,
          "usdc_size": 37125.02,
          "outcome": "Yes"
        }
      ]
    },
    {
      "wallet": "0x0164c35d78f87db2658044c2c64d92254c309ed6",
      "name": "poolcIeaner",
      "score": 41.8,
      "roi_score": 37.8,
      "calibration_score": 50.0,
      "consistency_score": 50.0,
      "early_entry_score": 0.0,
      "volume_score": 80.0,
      "roi": 6.7,
      "cash_pnl": 3477.3,
      "realized_pnl": 2095.91,
      "total_usdc": 36250.77,
      "trade_count": 500,
      "market_count": 56,
      "position_count": 59,
      "resolved_count": 0,
      "win_rate": 0,
      "z_score": 0.0,
      "last_active": "2026-07-02T10:51:41+00:00",
      "top_markets": [
        "Will Ivory Coast win the 2026 FIFA World Cup?",
        "Will Canada win the 2026 FIFA World Cup?",
        "Netherlands vs. Morocco: O/U 0.5"
      ],
      "signals": [
        {
          "market": "Will Switzerland win the 2026 FIFA World Cup?",
          "signal": "LATE",
          "avg_price": 0.0079,
          "cur_price": 0.0075,
          "usdc_size": 750.0,
          "outcome": "Yes"
        },
        {
          "market": "Will Spain win the 2026 FIFA World Cup?",
          "signal": "SKIP",
          "avg_price": 0.1378,
          "cur_price": 0.1005,
          "usdc_size": 1055.25,
          "outcome": "Yes"
        }
      ]
    },
    {
      "wallet": "0x09bed1976600971fd9f9db454a9c302c7a559c32",
      "name": "0x09beD1976600971Fd9f9Db454a9c302C7A559c32-1779171276281",
      "score": 41.5,
      "roi_score": 32.8,
      "calibration_score": 50.0,
      "consistency_score": 50.0,
      "early_entry_score": 0.0,
      "volume_score": 91.3,
      "roi": -0.7,
      "cash_pnl": -784.63,
      "realized_pnl": -4.81,
      "total_usdc": 159393.01,
      "trade_count": 273,
      "market_count": 67,
      "position_count": 20,
      "resolved_count": 0,
      "win_rate": 0,
      "z_score": 0.0,
      "last_active": "2026-07-02T10:38:20+00:00",
      "top_markets": [
        "Will the No to ten million Switzerland initiative be approved in Switzerland\u2019s June 14, 2026 popular vote?",
        "Will Arsenal FC win on 2026-05-30?",
        "Will Kimi Antonelli win the 2026 F1 Austrian Grand Prix?"
      ],
      "signals": [
        {
          "market": "Will Argentina win the 2026 FIFA World Cup?",
          "signal": "SKIP",
          "avg_price": 0.209,
          "cur_price": 0.1805,
          "usdc_size": 648.0,
          "outcome": "Yes"
        },
        {
          "market": "Will France win the 2026 FIFA World Cup?",
          "signal": "SKIP",
          "avg_price": 0.2113,
          "cur_price": 0.3505,
          "usdc_size": 1164.09,
          "outcome": "Yes"
        }
      ]
    },
    {
      "wallet": "0xb2005013643ecf63e84e653726e1a38450acbc94",
      "name": "aatf",
      "score": 41.5,
      "roi_score": 33.0,
      "calibration_score": 50.0,
      "consistency_score": 50.0,
      "early_entry_score": 0.0,
      "volume_score": 91.2,
      "roi": -0.5,
      "cash_pnl": -123.96,
      "realized_pnl": -48551.28,
      "total_usdc": 157904.89,
      "trade_count": 500,
      "market_count": 17,
      "position_count": 51,
      "resolved_count": 0,
      "win_rate": 0,
      "z_score": 0.0,
      "last_active": "2026-07-02T11:05:38+00:00",
      "top_markets": [
        "Will Portugal win the 2026 FIFA World Cup?",
        "Will France win the 2026 FIFA World Cup?",
        "Will Brazil win the 2026 FIFA World Cup?"
      ],
      "signals": [
        {
          "market": "Will Spain win the 2026 FIFA World Cup?",
          "signal": "SKIP",
          "avg_price": 0.5,
          "cur_price": 0.1005,
          "usdc_size": 2699.4,
          "outcome": "No"
        },
        {
          "market": "Will France win the 2026 FIFA World Cup?",
          "signal": "SKIP",
          "avg_price": 0.5,
          "cur_price": 0.3505,
          "usdc_size": 1051.54,
          "outcome": "Yes"
        },
        {
          "market": "Will Belgium win the 2026 FIFA World Cup?",
          "signal": "SKIP",
          "avg_price": 0.5,
          "cur_price": 0.0155,
          "usdc_size": 2953.51,
          "outcome": "No"
        },
        {
          "market": "Will Morocco win the 2026 FIFA World Cup?",
          "signal": "SKIP",
          "avg_price": 0.5,
          "cur_price": 0.0255,
          "usdc_size": 2923.51,
          "outcome": "No"
        },
        {
          "market": "Will Argentina win the 2026 FIFA World Cup?",
          "signal": "SKIP",
          "avg_price": 0.5,
          "cur_price": 0.1805,
          "usdc_size": 2458.49,
          "outcome": "No"
        },
        {
          "market": "Will England win the 2026 FIFA World Cup?",
          "signal": "SKIP",
          "avg_price": 0.5,
          "cur_price": 0.0825,
          "usdc_size": 2752.34,
          "outcome": "No"
        },
        {
          "market": "Will USA win the 2026 FIFA World Cup?",
          "signal": "SKIP",
          "avg_price": 0.5,
          "cur_price": 0.0275,
          "usdc_size": 2801.86,
          "outcome": "No"
        },
        {
          "market": "Will France win the 2026 FIFA World Cup?",
          "signal": "SKIP",
          "avg_price": 0.5,
          "cur_price": 0.3505,
          "usdc_size": 1103.5,
          "outcome": "No"
        },
        {
          "market": "Will Portugal win the 2026 FIFA World Cup?",
          "signal": "SKIP",
          "avg_price": 0.5,
          "cur_price": 0.0605,
          "usdc_size": 1145.25,
          "outcome": "No"
        },
        {
          "market": "Will Norway win the 2026 FIFA World Cup?",
          "signal": "SKIP",
          "avg_price": 0.5,
          "cur_price": 0.0195,
          "usdc_size": 895.21,
          "outcome": "No"
        },
        {
          "market": "Will Brazil win the 2026 FIFA World Cup?",
          "signal": "SKIP",
          "avg_price": 0.5,
          "cur_price": 0.0645,
          "usdc_size": 560.66,
          "outcome": "No"
        }
      ]
    },
    {
      "wallet": "0x81bc8f470d0a4281c1246fe2c10bf64088adfcfa",
      "name": "ball-GOD",
      "score": 41.4,
      "roi_score": 32.7,
      "calibration_score": 50.0,
      "consistency_score": 50.0,
      "early_entry_score": 0.0,
      "volume_score": 90.7,
      "roi": -0.9,
      "cash_pnl": -1220.01,
      "realized_pnl": 1375.49,
      "total_usdc": 147085.37,
      "trade_count": 500,
      "market_count": 61,
      "position_count": 31,
      "resolved_count": 0,
      "win_rate": 0,
      "z_score": 0.0,
      "last_active": "2026-07-02T09:23:22+00:00",
      "top_markets": [
        "Will Morocco win the 2026 FIFA World Cup?",
        "Will USA win the 2026 FIFA World Cup?",
        "Will Germany win the 2026 FIFA World Cup?"
      ],
      "signals": [
        {
          "market": "Will England win the 2026 FIFA World Cup?",
          "signal": "SKIP",
          "avg_price": 0.1128,
          "cur_price": 0.0825,
          "usdc_size": 12168.75,
          "outcome": "Yes"
        },
        {
          "market": "Will Spain win the 2026 FIFA World Cup?",
          "signal": "SKIP",
          "avg_price": 0.1662,
          "cur_price": 0.1005,
          "usdc_size": 14823.75,
          "outcome": "Yes"
        },
        {
          "market": "Will Brazil win the 2026 FIFA World Cup?",
          "signal": "SKIP",
          "avg_price": 0.089,
          "cur_price": 0.0645,
          "usdc_size": 9513.75,
          "outcome": "Yes"
        },
        {
          "market": "Will Argentina win the 2026 FIFA World Cup?",
          "signal": "SKIP",
          "avg_price": 0.0846,
          "cur_price": 0.1805,
          "usdc_size": 26623.73,
          "outcome": "Yes"
        },
        {
          "market": "Will France win the 2026 FIFA World Cup?",
          "signal": "SKIP",
          "avg_price": 0.174,
          "cur_price": 0.3505,
          "usdc_size": 51698.71,
          "outcome": "Yes"
        },
        {
          "market": "Will Portugal win the 2026 FIFA World Cup?",
          "signal": "SKIP",
          "avg_price": 0.0916,
          "cur_price": 0.0605,
          "usdc_size": 8923.74,
          "outcome": "Yes"
        },
        {
          "market": "Will Morocco win the 2026 FIFA World Cup?",
          "signal": "SKIP",
          "avg_price": 0.0288,
          "cur_price": 0.0255,
          "usdc_size": 3634.72,
          "outcome": "Yes"
        },
        {
          "market": "Will Switzerland win the 2026 FIFA World Cup?",
          "signal": "SKIP",
          "avg_price": 0.012,
          "cur_price": 0.0075,
          "usdc_size": 750.0,
          "outcome": "Yes"
        }
      ]
    },
    {
      "wallet": "0xcf8c7dd104740893eff7c1553bdc5f393fee670b",
      "name": "gaslia",
      "score": 40.9,
      "roi_score": 33.3,
      "calibration_score": 50.0,
      "consistency_score": 50.0,
      "early_entry_score": 0.0,
      "volume_score": 83.8,
      "roi": -0.1,
      "cash_pnl": -0.52,
      "realized_pnl": 0.0,
      "total_usdc": 59423.46,
      "trade_count": 108,
      "market_count": 42,
      "position_count": 1,
      "resolved_count": 0,
      "win_rate": 0,
      "z_score": 0.0,
      "last_active": "2026-07-02T04:24:56+00:00",
      "top_markets": [
        "Will Pump.fun perform an airdrop by December 31? ",
        "Will Crude Oil (CL) hit (HIGH) $200 by end of June?",
        "Will China invade Taiwan by June 30, 2026?"
      ],
      "signals": []
    },
    {
      "wallet": "0x36d6500083a30ef0148463e489c1e40bc1634547",
      "name": "jecob",
      "score": 40.6,
      "roi_score": 33.3,
      "calibration_score": 50.0,
      "consistency_score": 50.0,
      "early_entry_score": 0.0,
      "volume_score": 80.8,
      "roi": -0.1,
      "cash_pnl": -0.56,
      "realized_pnl": 0.0,
      "total_usdc": 40078.58,
      "trade_count": 112,
      "market_count": 49,
      "position_count": 1,
      "resolved_count": 0,
      "win_rate": 0,
      "z_score": 0.0,
      "last_active": "2026-07-02T03:36:19+00:00",
      "top_markets": [
        "Genius FDV above $1B one day after launch?",
        "Will the price of Bitcoin be above $62,000 on March 12?",
        "Will Bitcoin reach $150,000 in May?"
      ],
      "signals": []
    },
    {
      "wallet": "0x76ae25207b8b596b6e4efbe982bbf97dd506a90e",
      "name": "liangu",
      "score": 40.5,
      "roi_score": 33.3,
      "calibration_score": 50.0,
      "consistency_score": 50.0,
      "early_entry_score": 0.0,
      "volume_score": 80.4,
      "roi": -0.1,
      "cash_pnl": -0.44,
      "realized_pnl": 0.0,
      "total_usdc": 38054.23,
      "trade_count": 104,
      "market_count": 50,
      "position_count": 1,
      "resolved_count": 0,
      "win_rate": 0,
      "z_score": 0.0,
      "last_active": "2026-07-02T04:02:16+00:00",
      "top_markets": [
        "Will Bitcoin dip to $64,000 March 9-15?",
        "Will China invade Taiwan by June 30, 2026?",
        "Will the Fed decrease interest rates by 25 bps after the June 2026 meeting?"
      ],
      "signals": []
    },
    {
      "wallet": "0x6ae06eccd446342f96109e31eb7451383b511472",
      "name": "TraderSDG",
      "score": 40.5,
      "roi_score": 26.7,
      "calibration_score": 50.0,
      "consistency_score": 50.0,
      "early_entry_score": 0.0,
      "volume_score": 100.0,
      "roi": -9.9,
      "cash_pnl": -123238.68,
      "realized_pnl": 0.0,
      "total_usdc": 2743559.72,
      "trade_count": 388,
      "market_count": 18,
      "position_count": 9,
      "resolved_count": 0,
      "win_rate": 0,
      "z_score": 0.0,
      "last_active": "2026-07-01T21:03:34+00:00",
      "top_markets": [
        "Will Trump acquire Greenland before 2027?",
        "Xi Jinping out before 2027?",
        "Will Brazil win the 2026 FIFA World Cup?"
      ],
      "signals": [
        {
          "market": "Will England win the 2026 FIFA World Cup?",
          "signal": "SKIP",
          "avg_price": 0.898,
          "cur_price": 0.0825,
          "usdc_size": 91750.0,
          "outcome": "No"
        }
      ]
    },
    {
      "wallet": "0xe46fc309936825796cf2c73f5c6a28b895a7c0a8",
      "name": "papzini",
      "score": 40.2,
      "roi_score": 34.4,
      "calibration_score": 50.0,
      "consistency_score": 50.0,
      "early_entry_score": 0.0,
      "volume_score": 74.2,
      "roi": 1.6,
      "cash_pnl": 3.84,
      "realized_pnl": 0.0,
      "total_usdc": 16989.88,
      "trade_count": 268,
      "market_count": 111,
      "position_count": 1,
      "resolved_count": 0,
      "win_rate": 0,
      "z_score": 0.0,
      "last_active": "2026-07-02T09:06:44+00:00",
      "top_markets": [
        "US forces enter Iran by March 31?",
        "Will Brazil win the 2026 FIFA World Cup?",
        "Will Sporting CP win the UEFA Champions League?"
      ],
      "signals": []
    },
    {
      "wallet": "0xec5625bde94bdf224d6d941e612a403989921816",
      "name": "",
      "score": 39.8,
      "roi_score": 34.5,
      "calibration_score": 50.0,
      "consistency_score": 50.0,
      "early_entry_score": 0.0,
      "volume_score": 69.6,
      "roi": 1.8,
      "cash_pnl": 254.47,
      "realized_pnl": 12689.49,
      "total_usdc": 9206.35,
      "trade_count": 500,
      "market_count": 30,
      "position_count": 76,
      "resolved_count": 0,
      "win_rate": 0,
      "z_score": 0.0,
      "last_active": "2026-07-02T10:49:32+00:00",
      "top_markets": [
        "Will United States vs. Bosnia and Herzegovina end in a draw?",
        "United States vs. Bosnia and Herzegovina: Draw at halftime?",
        "United States vs. Bosnia and Herzegovina: Neither team to score first?"
      ],
      "signals": [
        {
          "market": "Will France win the 2026 FIFA World Cup?",
          "signal": "LATE",
          "avg_price": 0.3279,
          "cur_price": 0.3505,
          "usdc_size": 5824.33,
          "outcome": "Yes"
        }
      ]
    },
    {
      "wallet": "0x3f2eca848e5e4c19da9db7ac62f03c95ebdc05a6",
      "name": "SkillartSB",
      "score": 39.5,
      "roi_score": 31.4,
      "calibration_score": 50.0,
      "consistency_score": 50.0,
      "early_entry_score": 0.0,
      "volume_score": 75.8,
      "roi": -2.9,
      "cash_pnl": -689.98,
      "realized_pnl": 554.8,
      "total_usdc": 20878.5,
      "trade_count": 500,
      "market_count": 36,
      "position_count": 38,
      "resolved_count": 0,
      "win_rate": 0,
      "z_score": 0.0,
      "last_active": "2026-07-02T10:21:22+00:00",
      "top_markets": [
        "Will Andrey Rublev be the 2026 Men\u2019s Wimbledon winner?",
        "Will Daniil Medvedev be the 2026 Men\u2019s Wimbledon winner?",
        "Will Alexander Zverev be the 2026 Men\u2019s Wimbledon winner?"
      ],
      "signals": []
    },
    {
      "wallet": "0x24c8cf69a0e0a17eee21f69d29752bfa32e823e1",
      "name": "debased",
      "score": 39.0,
      "roi_score": 24.0,
      "calibration_score": 50.0,
      "consistency_score": 50.0,
      "early_entry_score": 0.0,
      "volume_score": 93.1,
      "roi": -13.9,
      "cash_pnl": -157394.69,
      "realized_pnl": 961092.2,
      "total_usdc": 202978.51,
      "trade_count": 500,
      "market_count": 22,
      "position_count": 161,
      "resolved_count": 0,
      "win_rate": 0,
      "z_score": 0.0,
      "last_active": "2026-07-02T10:21:29+00:00",
      "top_markets": [
        "Will Mexico win the 2026 FIFA World Cup?",
        "Will Belgium win the 2026 FIFA World Cup?",
        "Will Ecuador win the 2026 FIFA World Cup?"
      ],
      "signals": [
        {
          "market": "Will Brazil win the 2026 FIFA World Cup?",
          "signal": "ENTER",
          "avg_price": 0.0657,
          "cur_price": 0.0645,
          "usdc_size": 5192.91,
          "outcome": "Yes"
        },
        {
          "market": "Will Portugal win the 2026 FIFA World Cup?",
          "signal": "ENTER",
          "avg_price": 0.0602,
          "cur_price": 0.0605,
          "usdc_size": 4529.62,
          "outcome": "Yes"
        },
        {
          "market": "Will USA win the 2026 FIFA World Cup?",
          "signal": "LATE",
          "avg_price": 0.0266,
          "cur_price": 0.0275,
          "usdc_size": 3224.7,
          "outcome": "Yes"
        },
        {
          "market": "Will Argentina win the 2026 FIFA World Cup?",
          "signal": "LATE",
          "avg_price": 0.1905,
          "cur_price": 0.1805,
          "usdc_size": 12849.39,
          "outcome": "Yes"
        },
        {
          "market": "Will Belgium win the 2026 FIFA World Cup?",
          "signal": "LATE",
          "avg_price": 0.0149,
          "cur_price": 0.0155,
          "usdc_size": 1033.32,
          "outcome": "Yes"
        },
        {
          "market": "Will Norway win the 2026 FIFA World Cup?",
          "signal": "SKIP",
          "avg_price": 0.023,
          "cur_price": 0.0195,
          "usdc_size": 6173.38,
          "outcome": "Yes"
        },
        {
          "market": "Will Mexico win the 2026 FIFA World Cup?",
          "signal": "SKIP",
          "avg_price": 0.0294,
          "cur_price": 0.0345,
          "usdc_size": 4906.9,
          "outcome": "Yes"
        },
        {
          "market": "Will England win the 2026 FIFA World Cup?",
          "signal": "SKIP",
          "avg_price": 0.0913,
          "cur_price": 0.0825,
          "usdc_size": 6576.76,
          "outcome": "Yes"
        },
        {
          "market": "Will Morocco win the 2026 FIFA World Cup?",
          "signal": "SKIP",
          "avg_price": 0.0193,
          "cur_price": 0.0255,
          "usdc_size": 1865.03,
          "outcome": "Yes"
        },
        {
          "market": "Will France win the 2026 FIFA World Cup?",
          "signal": "SKIP",
          "avg_price": 0.2644,
          "cur_price": 0.3505,
          "usdc_size": 24161.65,
          "outcome": "Yes"
        },
        {
          "market": "Will Spain win the 2026 FIFA World Cup?",
          "signal": "SKIP",
          "avg_price": 0.111,
          "cur_price": 0.1005,
          "usdc_size": 6853.72,
          "outcome": "Yes"
        }
      ]
    },
    {
      "wallet": "0x6a678ca367432d28cb6aa55bb6bc57d8f53bdf6f",
      "name": "Runner109",
      "score": 38.3,
      "roi_score": 32.9,
      "calibration_score": 50.0,
      "consistency_score": 50.0,
      "early_entry_score": 0.0,
      "volume_score": 59.0,
      "roi": -0.6,
      "cash_pnl": -293.27,
      "realized_pnl": 8334.41,
      "total_usdc": 2292.07,
      "trade_count": 500,
      "market_count": 6,
      "position_count": 29,
      "resolved_count": 0,
      "win_rate": 0,
      "z_score": 0.0,
      "last_active": "2026-07-02T11:06:46+00:00",
      "top_markets": [
        "Will Switzerland win the 2026 FIFA World Cup?",
        "Will Morocco win the 2026 FIFA World Cup?",
        "Will Austria reach the Round of 16 at the 2026 FIFA World Cup?"
      ],
      "signals": [
        {
          "market": "Will Brazil win the 2026 FIFA World Cup?",
          "signal": "ENTER",
          "avg_price": 0.0661,
          "cur_price": 0.0645,
          "usdc_size": 3491.22,
          "outcome": "Yes"
        },
        {
          "market": "Will Morocco win the 2026 FIFA World Cup?",
          "signal": "LATE",
          "avg_price": 0.0271,
          "cur_price": 0.0255,
          "usdc_size": 15073.44,
          "outcome": "Yes"
        },
        {
          "market": "Will Switzerland win the 2026 FIFA World Cup?",
          "signal": "LATE",
          "avg_price": 0.007,
          "cur_price": 0.0075,
          "usdc_size": 2938.33,
          "outcome": "Yes"
        },
        {
          "market": "Will Norway win the 2026 FIFA World Cup?",
          "signal": "LATE",
          "avg_price": 0.0208,
          "cur_price": 0.0195,
          "usdc_size": 3309.15,
          "outcome": "Yes"
        },
        {
          "market": "Will Spain win the 2026 FIFA World Cup?",
          "signal": "SKIP",
          "avg_price": 0.1174,
          "cur_price": 0.1005,
          "usdc_size": 4824.0,
          "outcome": "Yes"
        }
      ]
    },
    {
      "wallet": "0xf49ce459b52f60b70ce0fe9aa6203e6bf90f9786",
      "name": "TradingWave",
      "score": 35.9,
      "roi_score": 29.5,
      "calibration_score": 50.0,
      "consistency_score": 50.0,
      "early_entry_score": 0.0,
      "volume_score": 45.3,
      "roi": -5.7,
      "cash_pnl": -19680.38,
      "realized_pnl": 42295.55,
      "total_usdc": 383.6,
      "trade_count": 500,
      "market_count": 8,
      "position_count": 114,
      "resolved_count": 0,
      "win_rate": 0,
      "z_score": 0.0,
      "last_active": "2026-07-02T11:03:43+00:00",
      "top_markets": [
        "Will Canada win the 2026 FIFA World Cup?",
        "Will Australia win the 2026 FIFA World Cup?",
        "Will Egypt win the 2026 FIFA World Cup?"
      ],
      "signals": [
        {
          "market": "Will Ghana win the 2026 FIFA World Cup?",
          "signal": "LATE",
          "avg_price": 0.001,
          "cur_price": 0.0005,
          "usdc_size": 3242.65,
          "outcome": "Yes"
        },
        {
          "market": "Will Algeria win the 2026 FIFA World Cup?",
          "signal": "LATE",
          "avg_price": 0.001,
          "cur_price": 0.0005,
          "usdc_size": 2647.41,
          "outcome": "Yes"
        },
        {
          "market": "Will Paraguay win the 2026 FIFA World Cup?",
          "signal": "LATE",
          "avg_price": 0.001,
          "cur_price": 0.0015,
          "usdc_size": 4975.45,
          "outcome": "Yes"
        },
        {
          "market": "Will Australia win the 2026 FIFA World Cup?",
          "signal": "LATE",
          "avg_price": 0.001,
          "cur_price": 0.0015,
          "usdc_size": 1703.05,
          "outcome": "Yes"
        },
        {
          "market": "Will Belgium win the 2026 FIFA World Cup?",
          "signal": "LATE",
          "avg_price": 0.015,
          "cur_price": 0.0155,
          "usdc_size": 14994.72,
          "outcome": "Yes"
        },
        {
          "market": "Will Croatia win the 2026 FIFA World Cup?",
          "signal": "SKIP",
          "avg_price": 0.0048,
          "cur_price": 0.0035,
          "usdc_size": 10384.3,
          "outcome": "Yes"
        },
        {
          "market": "Will Mexico win the 2026 FIFA World Cup?",
          "signal": "SKIP",
          "avg_price": 0.0123,
          "cur_price": 0.0345,
          "usdc_size": 37949.99,
          "outcome": "Yes"
        },
        {
          "market": "Will Morocco win the 2026 FIFA World Cup?",
          "signal": "SKIP",
          "avg_price": 0.0172,
          "cur_price": 0.0255,
          "usdc_size": 23088.91,
          "outcome": "Yes"
        },
        {
          "market": "Will USA win the 2026 FIFA World Cup?",
          "signal": "SKIP",
          "avg_price": 0.0216,
          "cur_price": 0.0275,
          "usdc_size": 20905.29,
          "outcome": "Yes"
        },
        {
          "market": "Will Norway win the 2026 FIFA World Cup?",
          "signal": "SKIP",
          "avg_price": 0.0236,
          "cur_price": 0.0195,
          "usdc_size": 8405.53,
          "outcome": "Yes"
        },
        {
          "market": "Will England win the 2026 FIFA World Cup?",
          "signal": "SKIP",
          "avg_price": 0.1043,
          "cur_price": 0.0825,
          "usdc_size": 28599.42,
          "outcome": "Yes"
        },
        {
          "market": "Will Portugal win the 2026 FIFA World Cup?",
          "signal": "SKIP",
          "avg_price": 0.0719,
          "cur_price": 0.0605,
          "usdc_size": 16637.48,
          "outcome": "Yes"
        },
        {
          "market": "Will Brazil win the 2026 FIFA World Cup?",
          "signal": "SKIP",
          "avg_price": 0.0839,
          "cur_price": 0.0645,
          "usdc_size": 17737.4,
          "outcome": "Yes"
        },
        {
          "market": "Will Spain win the 2026 FIFA World Cup?",
          "signal": "SKIP",
          "avg_price": 0.1224,
          "cur_price": 0.1005,
          "usdc_size": 15075.0,
          "outcome": "Yes"
        }
      ]
    },
    {
      "wallet": "0x36bd0412539892373be60df52c3ffa56f6183263",
      "name": "Thomas-Anderson",
      "score": 35.9,
      "roi_score": 19.0,
      "calibration_score": 50.0,
      "consistency_score": 50.0,
      "early_entry_score": 0.0,
      "volume_score": 76.8,
      "roi": -21.4,
      "cash_pnl": -1274.68,
      "realized_pnl": -1845.82,
      "total_usdc": 23809.19,
      "trade_count": 45,
      "market_count": 3,
      "position_count": 2,
      "resolved_count": 0,
      "win_rate": 0,
      "z_score": 0.0,
      "last_active": "2026-07-01T17:41:32+00:00",
      "top_markets": [
        "Will Belgium win the 2026 FIFA World Cup?",
        "Will Portugal win the 2026 FIFA World Cup?",
        "Will England win the 2026 FIFA World Cup?"
      ],
      "signals": [
        {
          "market": "Will England win the 2026 FIFA World Cup?",
          "signal": "SKIP",
          "avg_price": 0.105,
          "cur_price": 0.0825,
          "usdc_size": 4673.82,
          "outcome": "Yes"
        }
      ]
    },
    {
      "wallet": "0xe542afd3881c4c330ba0ebbb603bb470b2ba0a37",
      "name": "leegunner",
      "score": 35.1,
      "roi_score": 15.8,
      "calibration_score": 50.0,
      "consistency_score": 50.0,
      "early_entry_score": 0.0,
      "volume_score": 78.7,
      "roi": -26.3,
      "cash_pnl": -32051.56,
      "realized_pnl": 41388.31,
      "total_usdc": 30684.65,
      "trade_count": 500,
      "market_count": 50,
      "position_count": 500,
      "resolved_count": 0,
      "win_rate": 0,
      "z_score": 0.0,
      "last_active": "2026-07-02T10:23:23+00:00",
      "top_markets": [
        "Will Oklahoma City Thunder win the 2027 NBA Finals?",
        "Will Belgium win the 2026 FIFA World Cup?",
        "Will LeBron James play for the Minnesota Timberwolves in 2026-27?"
      ],
      "signals": [
        {
          "market": "Will Australia win the 2026 FIFA World Cup?",
          "signal": "ENTER",
          "avg_price": 0.0015,
          "cur_price": 0.0015,
          "usdc_size": 1203.91,
          "outcome": "Yes"
        }
      ]
    },
    {
      "wallet": "0x8e77537e059837d3c2ca5b4efe75e74e9498c4f3",
      "name": "dwpoker",
      "score": 34.1,
      "roi_score": 5.4,
      "calibration_score": 50.0,
      "consistency_score": 50.0,
      "early_entry_score": 0.0,
      "volume_score": 100.0,
      "roi": -41.9,
      "cash_pnl": -131061.08,
      "realized_pnl": 11696.94,
      "total_usdc": 498098.36,
      "trade_count": 500,
      "market_count": 68,
      "position_count": 105,
      "resolved_count": 0,
      "win_rate": 0,
      "z_score": 0.0,
      "last_active": "2026-07-02T08:42:25+00:00",
      "top_markets": [
        "Kharg Island no longer under Iranian control by June 30?",
        "Trump out as President by June 30?",
        "Iran closes its airspace by May 24?"
      ],
      "signals": [
        {
          "market": "Will France win the 2026 FIFA World Cup?",
          "signal": "ENTER",
          "avg_price": 0.3439,
          "cur_price": 0.3505,
          "usdc_size": 876.25,
          "outcome": "Yes"
        }
      ]
    },
    {
      "wallet": "0x8044886b3d8ee80e7bb0e202495d50491bedac75",
      "name": "Wolf771",
      "score": 33.8,
      "roi_score": 11.1,
      "calibration_score": 50.0,
      "consistency_score": 50.0,
      "early_entry_score": 0.0,
      "volume_score": 79.7,
      "roi": -33.4,
      "cash_pnl": -4929.85,
      "realized_pnl": 221.84,
      "total_usdc": 34827.87,
      "trade_count": 256,
      "market_count": 117,
      "position_count": 59,
      "resolved_count": 0,
      "win_rate": 0,
      "z_score": 0.0,
      "last_active": "2026-07-01T22:59:14+00:00",
      "top_markets": [
        "Will Norway win the 2026 FIFA World Cup?",
        "Will Scottie Scheffler win the 2026 Masters tournament?",
        "Will Pope Leo XIV win the Nobel Peace Prize in 2026?"
      ],
      "signals": [
        {
          "market": "Will Argentina win the 2026 FIFA World Cup?",
          "signal": "ENTER",
          "avg_price": 0.1799,
          "cur_price": 0.1805,
          "usdc_size": 1002.78,
          "outcome": "Yes"
        },
        {
          "market": "Will Switzerland win the 2026 FIFA World Cup?",
          "signal": "SKIP",
          "avg_price": 0.009,
          "cur_price": 0.0075,
          "usdc_size": 833.33,
          "outcome": "Yes"
        },
        {
          "market": "Will Morocco win the 2026 FIFA World Cup?",
          "signal": "SKIP",
          "avg_price": 0.0375,
          "cur_price": 0.0255,
          "usdc_size": 954.81,
          "outcome": "Yes"
        },
        {
          "market": "Will Portugal win the 2026 FIFA World Cup?",
          "signal": "SKIP",
          "avg_price": 0.0725,
          "cur_price": 0.0605,
          "usdc_size": 833.73,
          "outcome": "Yes"
        },
        {
          "market": "Will France win the 2026 FIFA World Cup?",
          "signal": "SKIP",
          "avg_price": 0.1859,
          "cur_price": 0.3505,
          "usdc_size": 2826.98,
          "outcome": "Yes"
        }
      ]
    },
    {
      "wallet": "0x7ff0e44bd6c217e182c0dea081ad638b87ac8e88",
      "name": "ArthurCoach",
      "score": 32.8,
      "roi_score": 10.2,
      "calibration_score": 50.0,
      "consistency_score": 50.0,
      "early_entry_score": 0.0,
      "volume_score": 72.0,
      "roi": -34.6,
      "cash_pnl": -2447.02,
      "realized_pnl": 0.0,
      "total_usdc": 12617.15,
      "trade_count": 15,
      "market_count": 11,
      "position_count": 7,
      "resolved_count": 0,
      "win_rate": 0,
      "z_score": 0.0,
      "last_active": "2026-07-02T02:13:56+00:00",
      "top_markets": [
        "Will USA win the 2026 FIFA World Cup?",
        "Will Belgium win the 2026 FIFA World Cup?",
        "Will Portugal win the 2026 FIFA World Cup?"
      ],
      "signals": [
        {
          "market": "Will Argentina win the 2026 FIFA World Cup?",
          "signal": "SKIP",
          "avg_price": 0.1179,
          "cur_price": 0.1805,
          "usdc_size": 1791.4,
          "outcome": "Yes"
        },
        {
          "market": "Will France win the 2026 FIFA World Cup?",
          "signal": "SKIP",
          "avg_price": 0.1609,
          "cur_price": 0.3505,
          "usdc_size": 2177.02,
          "outcome": "Yes"
        },
        {
          "market": "Will Spain win the 2026 FIFA World Cup?",
          "signal": "SKIP",
          "avg_price": 0.1679,
          "cur_price": 0.1005,
          "usdc_size": 598.21,
          "outcome": "Yes"
        }
      ]
    },
    {
      "wallet": "0x83720820a8aa6c3f20ad71850e7a1a17d16c5223",
      "name": "Jsram",
      "score": 32.4,
      "roi_score": 0.0,
      "calibration_score": 50.0,
      "consistency_score": 50.0,
      "early_entry_score": 0.0,
      "volume_score": 98.8,
      "roi": -72.1,
      "cash_pnl": -1713327.93,
      "realized_pnl": 0.0,
      "total_usdc": 427719.61,
      "trade_count": 500,
      "market_count": 9,
      "position_count": 57,
      "resolved_count": 0,
      "win_rate": 0,
      "z_score": 0.0,
      "last_active": "2026-07-02T08:05:34+00:00",
      "top_markets": [
        "Belgium vs. Senegal: Both Teams to Score",
        "Mexico vs. Ecuador: Team to Advance",
        "Will Brazil win the 2026 FIFA World Cup?"
      ],
      "signals": [
        {
          "market": "Will Switzerland win the 2026 FIFA World Cup?",
          "signal": "LATE",
          "avg_price": 0.0081,
          "cur_price": 0.0075,
          "usdc_size": 29559.52,
          "outcome": "Yes"
        },
        {
          "market": "Will Brazil win the 2026 FIFA World Cup?",
          "signal": "LATE",
          "avg_price": 0.0621,
          "cur_price": 0.0645,
          "usdc_size": 100233.05,
          "outcome": "Yes"
        },
        {
          "market": "Will Belgium win the 2026 FIFA World Cup?",
          "signal": "SKIP",
          "avg_price": 0.0127,
          "cur_price": 0.0155,
          "usdc_size": 39630.28,
          "outcome": "Yes"
        },
        {
          "market": "Will England win the 2026 FIFA World Cup?",
          "signal": "SKIP",
          "avg_price": 0.1136,
          "cur_price": 0.0825,
          "usdc_size": 186897.47,
          "outcome": "Yes"
        },
        {
          "market": "Will Morocco win the 2026 FIFA World Cup?",
          "signal": "SKIP",
          "avg_price": 0.0207,
          "cur_price": 0.0255,
          "usdc_size": 20530.11,
          "outcome": "Yes"
        },
        {
          "market": "Will Spain win the 2026 FIFA World Cup?",
          "signal": "SKIP",
          "avg_price": 0.122,
          "cur_price": 0.1005,
          "usdc_size": 64381.64,
          "outcome": "Yes"
        },
        {
          "market": "Will France win the 2026 FIFA World Cup?",
          "signal": "SKIP",
          "avg_price": 0.1842,
          "cur_price": 0.3505,
          "usdc_size": 109404.53,
          "outcome": "Yes"
        },
        {
          "market": "Will Portugal win the 2026 FIFA World Cup?",
          "signal": "SKIP",
          "avg_price": 0.0669,
          "cur_price": 0.0605,
          "usdc_size": 3611.94,
          "outcome": "Yes"
        }
      ]
    },
    {
      "wallet": "0x2663daca3cecf3767ca1c3b126002a8578a8ed1f",
      "name": "Q96s3kwozynxpau",
      "score": 32.1,
      "roi_score": 5.0,
      "calibration_score": 50.0,
      "consistency_score": 50.0,
      "early_entry_score": 0.0,
      "volume_score": 81.3,
      "roi": -42.6,
      "cash_pnl": -104258.4,
      "realized_pnl": -804496.36,
      "total_usdc": 43061.47,
      "trade_count": 500,
      "market_count": 35,
      "position_count": 163,
      "resolved_count": 0,
      "win_rate": 0,
      "z_score": 0.0,
      "last_active": "2026-07-02T11:05:46+00:00",
      "top_markets": [
        "Will Spain win the 2026 FIFA World Cup?",
        "Will Croatia win the 2026 FIFA World Cup?",
        "Will Mexico win the 2026 FIFA World Cup?"
      ],
      "signals": [
        {
          "market": "Will Belgium win the 2026 FIFA World Cup?",
          "signal": "LATE",
          "avg_price": 0.0166,
          "cur_price": 0.0155,
          "usdc_size": 1895.71,
          "outcome": "Yes"
        },
        {
          "market": "Will Australia win the 2026 FIFA World Cup?",
          "signal": "SKIP",
          "avg_price": 0.015,
          "cur_price": 0.0015,
          "usdc_size": 3296.52,
          "outcome": "Yes"
        },
        {
          "market": "Will Switzerland win the 2026 FIFA World Cup?",
          "signal": "SKIP",
          "avg_price": 0.015,
          "cur_price": 0.0075,
          "usdc_size": 12194.35,
          "outcome": "Yes"
        },
        {
          "market": "Will Algeria win the 2026 FIFA World Cup?",
          "signal": "SKIP",
          "avg_price": 0.0166,
          "cur_price": 0.0005,
          "usdc_size": 605.54,
          "outcome": "Yes"
        },
        {
          "market": "Will Croatia win the 2026 FIFA World Cup?",
          "signal": "SKIP",
          "avg_price": 0.0092,
          "cur_price": 0.0035,
          "usdc_size": 3919.94,
          "outcome": "Yes"
        },
        {
          "market": "Will Paraguay win the 2026 FIFA World Cup?",
          "signal": "SKIP",
          "avg_price": 0.0166,
          "cur_price": 0.0015,
          "usdc_size": 945.03,
          "outcome": "Yes"
        },
        {
          "market": "Will Mexico win the 2026 FIFA World Cup?",
          "signal": "SKIP",
          "avg_price": 0.0256,
          "cur_price": 0.0345,
          "usdc_size": 3050.26,
          "outcome": "Yes"
        },
        {
          "market": "Will France win the 2026 FIFA World Cup?",
          "signal": "SKIP",
          "avg_price": 0.0166,
          "cur_price": 0.3505,
          "usdc_size": 25408.16,
          "outcome": "Yes"
        },
        {
          "market": "Will Argentina win the 2026 FIFA World Cup?",
          "signal": "SKIP",
          "avg_price": 0.0166,
          "cur_price": 0.1805,
          "usdc_size": 12742.92,
          "outcome": "Yes"
        },
        {
          "market": "Will England win the 2026 FIFA World Cup?",
          "signal": "SKIP",
          "avg_price": 0.0166,
          "cur_price": 0.0825,
          "usdc_size": 3729.36,
          "outcome": "Yes"
        },
        {
          "market": "Will USA win the 2026 FIFA World Cup?",
          "signal": "SKIP",
          "avg_price": 0.0166,
          "cur_price": 0.0275,
          "usdc_size": 1237.99,
          "outcome": "Yes"
        },
        {
          "market": "Will Morocco win the 2026 FIFA World Cup?",
          "signal": "SKIP",
          "avg_price": 0.0166,
          "cur_price": 0.0255,
          "usdc_size": 989.68,
          "outcome": "Yes"
        },
        {
          "market": "Will Brazil win the 2026 FIFA World Cup?",
          "signal": "SKIP",
          "avg_price": 0.0166,
          "cur_price": 0.0645,
          "usdc_size": 2415.72,
          "outcome": "Yes"
        },
        {
          "market": "Will Portugal win the 2026 FIFA World Cup?",
          "signal": "SKIP",
          "avg_price": 0.0166,
          "cur_price": 0.0605,
          "usdc_size": 970.41,
          "outcome": "Yes"
        },
        {
          "market": "Will Spain win the 2026 FIFA World Cup?",
          "signal": "SKIP",
          "avg_price": 0.4999,
          "cur_price": 0.1005,
          "usdc_size": 1611.99,
          "outcome": "Yes"
        }
      ]
    },
    {
      "wallet": "0x99c4fb1f78881601075bc25b13c9af76bc5918e7",
      "name": "definitelyNotBot",
      "score": 32.0,
      "roi_score": 0.0,
      "calibration_score": 50.0,
      "consistency_score": 50.0,
      "early_entry_score": 0.0,
      "volume_score": 95.2,
      "roi": -61.3,
      "cash_pnl": -62292.18,
      "realized_pnl": 567137.98,
      "total_usdc": 264661.95,
      "trade_count": 500,
      "market_count": 6,
      "position_count": 31,
      "resolved_count": 0,
      "win_rate": 0,
      "z_score": 0.0,
      "last_active": "2026-07-02T02:07:20+00:00",
      "top_markets": [
        "United States vs. Bosnia and Herzegovina: Team to Advance",
        "Will USA win the 2026 FIFA World Cup?",
        "Will United States win on 2026-07-01?"
      ],
      "signals": [
        {
          "market": "Will Norway win the 2026 FIFA World Cup?",
          "signal": "SKIP",
          "avg_price": 0.0224,
          "cur_price": 0.0195,
          "usdc_size": 682.69,
          "outcome": "Yes"
        }
      ]
    },
    {
      "wallet": "0xe5241830e8876c115d7dc8311ad9f43d85fdd34f",
      "name": "Sportbetting76",
      "score": 31.9,
      "roi_score": 0.0,
      "calibration_score": 50.0,
      "consistency_score": 50.0,
      "early_entry_score": 0.0,
      "volume_score": 93.9,
      "roi": -57.3,
      "cash_pnl": -74936.77,
      "realized_pnl": 0.0,
      "total_usdc": 224850.18,
      "trade_count": 500,
      "market_count": 32,
      "position_count": 24,
      "resolved_count": 0,
      "win_rate": 0,
      "z_score": 0.0,
      "last_active": "2026-07-02T01:34:58+00:00",
      "top_markets": [
        "United States vs. Bosnia and Herzegovina: Both Teams to Score",
        "C\u00f4te d'Ivoire vs. Norway: Both Teams to Score",
        "Will Switzerland win the 2026 FIFA World Cup?"
      ],
      "signals": [
        {
          "market": "Will Belgium win the 2026 FIFA World Cup?",
          "signal": "LATE",
          "avg_price": 0.015,
          "cur_price": 0.0155,
          "usdc_size": 1585.39,
          "outcome": "Yes"
        },
        {
          "market": "Will Switzerland win the 2026 FIFA World Cup?",
          "signal": "SKIP",
          "avg_price": 0.009,
          "cur_price": 0.0075,
          "usdc_size": 2051.72,
          "outcome": "Yes"
        },
        {
          "market": "Will Morocco win the 2026 FIFA World Cup?",
          "signal": "SKIP",
          "avg_price": 0.0125,
          "cur_price": 0.0255,
          "usdc_size": 5842.0,
          "outcome": "Yes"
        },
        {
          "market": "Will Spain win the 2026 FIFA World Cup?",
          "signal": "SKIP",
          "avg_price": 0.136,
          "cur_price": 0.1005,
          "usdc_size": 20100.0,
          "outcome": "Yes"
        },
        {
          "market": "Will Norway win the 2026 FIFA World Cup?",
          "signal": "SKIP",
          "avg_price": 0.0232,
          "cur_price": 0.0195,
          "usdc_size": 2650.91,
          "outcome": "Yes"
        },
        {
          "market": "Will England win the 2026 FIFA World Cup?",
          "signal": "SKIP",
          "avg_price": 0.0986,
          "cur_price": 0.0825,
          "usdc_size": 10327.19,
          "outcome": "Yes"
        }
      ]
    },
    {
      "wallet": "0xb3cfe7615d64db8dfa743a1b1a2b976911460ebd",
      "name": "omoi0i0",
      "score": 31.8,
      "roi_score": 0.0,
      "calibration_score": 50.0,
      "consistency_score": 50.0,
      "early_entry_score": 0.0,
      "volume_score": 93.2,
      "roi": -90.9,
      "cash_pnl": -886651.65,
      "realized_pnl": 209295.61,
      "total_usdc": 206109.2,
      "trade_count": 500,
      "market_count": 53,
      "position_count": 500,
      "resolved_count": 0,
      "win_rate": 0,
      "z_score": 0.0,
      "last_active": "2026-07-02T09:22:37+00:00",
      "top_markets": [
        "Argentina vs. Cabo Verde: Team to Advance",
        "Will Mexico win the 2026 FIFA World Cup?",
        "France vs. Sweden: Team to Advance"
      ],
      "signals": [
        {
          "market": "Will Brazil win the 2026 FIFA World Cup?",
          "signal": "ENTER",
          "avg_price": 0.0654,
          "cur_price": 0.0645,
          "usdc_size": 645.0,
          "outcome": "Yes"
        },
        {
          "market": "Will USA win the 2026 FIFA World Cup?",
          "signal": "LATE",
          "avg_price": 0.0265,
          "cur_price": 0.0275,
          "usdc_size": 7600.56,
          "outcome": "Yes"
        },
        {
          "market": "Will Belgium win the 2026 FIFA World Cup?",
          "signal": "SKIP",
          "avg_price": 0.009,
          "cur_price": 0.0155,
          "usdc_size": 2799.78,
          "outcome": "Yes"
        },
        {
          "market": "Will Mexico win the 2026 FIFA World Cup?",
          "signal": "SKIP",
          "avg_price": 0.0215,
          "cur_price": 0.0345,
          "usdc_size": 6029.62,
          "outcome": "Yes"
        },
        {
          "market": "Will France win the 2026 FIFA World Cup?",
          "signal": "SKIP",
          "avg_price": 0.2431,
          "cur_price": 0.3505,
          "usdc_size": 7365.18,
          "outcome": "Yes"
        },
        {
          "market": "Will Portugal win the 2026 FIFA World Cup?",
          "signal": "SKIP",
          "avg_price": 0.082,
          "cur_price": 0.0605,
          "usdc_size": 1210.0,
          "outcome": "Yes"
        }
      ]
    },
    {
      "wallet": "0x4154ffdc11d057087ea5b67fda6e1388ac8ee7a8",
      "name": "acfc8",
      "score": 31.7,
      "roi_score": 0.0,
      "calibration_score": 50.0,
      "consistency_score": 50.0,
      "early_entry_score": 0.0,
      "volume_score": 92.2,
      "roi": -81.1,
      "cash_pnl": -157570.48,
      "realized_pnl": -1134.77,
      "total_usdc": 178941.77,
      "trade_count": 500,
      "market_count": 42,
      "position_count": 137,
      "resolved_count": 0,
      "win_rate": 0,
      "z_score": 0.0,
      "last_active": "2026-07-02T09:22:28+00:00",
      "top_markets": [
        "Belgium vs. Senegal: Team to Advance",
        "Exact Score: Any Other Score?",
        "England vs. DR Congo: DR Congo O/U 2.5 Corners"
      ],
      "signals": []
    },
    {
      "wallet": "0x8c0b024c17831a0dde038547b7e791ae6a0d7aa5",
      "name": "CANTSTANDIT",
      "score": 31.7,
      "roi_score": 0.0,
      "calibration_score": 50.0,
      "consistency_score": 50.0,
      "early_entry_score": 0.0,
      "volume_score": 92.3,
      "roi": -98.5,
      "cash_pnl": -1444317.91,
      "realized_pnl": 32806.13,
      "total_usdc": 182997.75,
      "trade_count": 500,
      "market_count": 11,
      "position_count": 461,
      "resolved_count": 0,
      "win_rate": 0,
      "z_score": 0.0,
      "last_active": "2026-07-02T10:51:32+00:00",
      "top_markets": [
        "Spread: United States (-1.5)",
        "Will Belgium win on 2026-07-01?",
        "LoL: Bilibili Gaming vs T1 (BO5) - Mid-Season Invitational Playoffs"
      ],
      "signals": [
        {
          "market": "Will Paraguay win the 2026 FIFA World Cup?",
          "signal": "LATE",
          "avg_price": 0.002,
          "cur_price": 0.0015,
          "usdc_size": 1204.79,
          "outcome": "Yes"
        },
        {
          "market": "Will Belgium win the 2026 FIFA World Cup?",
          "signal": "LATE",
          "avg_price": 0.0148,
          "cur_price": 0.0155,
          "usdc_size": 5124.95,
          "outcome": "Yes"
        }
      ]
    },
    {
      "wallet": "0xda0f4e3f79a50b8601b3cb9d421f48ce11bbf0e7",
      "name": "Xplayer",
      "score": 31.3,
      "roi_score": 0.0,
      "calibration_score": 50.0,
      "consistency_score": 50.0,
      "early_entry_score": 0.0,
      "volume_score": 88.3,
      "roi": -94.3,
      "cash_pnl": -3645.74,
      "realized_pnl": 888.09,
      "total_usdc": 107763.56,
      "trade_count": 500,
      "market_count": 49,
      "position_count": 20,
      "resolved_count": 0,
      "win_rate": 0,
      "z_score": 0.0,
      "last_active": "2026-07-02T11:04:13+00:00",
      "top_markets": [
        "Will Belgium win the 2026 FIFA World Cup?",
        "Will Falcons win IEM Cologne Major 2026?",
        "Will France win the 2026 FIFA World Cup?"
      ],
      "signals": []
    },
    {
      "wallet": "0xb22598b366c9ec16a3e97dc90e09dd5fd8dc3d54",
      "name": "0xb22598b366c9ec16A3e97dc90e09dd5fD8dc3d54-1762701017684",
      "score": 31.1,
      "roi_score": 0.0,
      "calibration_score": 50.0,
      "consistency_score": 50.0,
      "early_entry_score": 0.0,
      "volume_score": 86.0,
      "roi": -78.0,
      "cash_pnl": -113879.65,
      "realized_pnl": 0.0,
      "total_usdc": 80008.65,
      "trade_count": 500,
      "market_count": 11,
      "position_count": 35,
      "resolved_count": 0,
      "win_rate": 0,
      "z_score": 0.0,
      "last_active": "2026-07-02T11:06:07+00:00",
      "top_markets": [
        "C\u00f4te d'Ivoire vs. Norway: Team to Advance",
        "Will Brazil win the 2026 FIFA World Cup?",
        "Will England win the 2026 FIFA World Cup?"
      ],
      "signals": [
        {
          "market": "Will England win the 2026 FIFA World Cup?",
          "signal": "ENTER",
          "avg_price": 0.082,
          "cur_price": 0.0825,
          "usdc_size": 5118.45,
          "outcome": "Yes"
        },
        {
          "market": "Will Brazil win the 2026 FIFA World Cup?",
          "signal": "ENTER",
          "avg_price": 0.064,
          "cur_price": 0.0645,
          "usdc_size": 3530.84,
          "outcome": "Yes"
        },
        {
          "market": "Will Portugal win the 2026 FIFA World Cup?",
          "signal": "LATE",
          "avg_price": 0.057,
          "cur_price": 0.0605,
          "usdc_size": 3025.0,
          "outcome": "Yes"
        },
        {
          "market": "Will Belgium win the 2026 FIFA World Cup?",
          "signal": "SKIP",
          "avg_price": 0.014,
          "cur_price": 0.0155,
          "usdc_size": 904.26,
          "outcome": "Yes"
        }
      ]
    },
    {
      "wallet": "0x6db983ff1cbc85249e64e6ccd101aaa613ba4ab5",
      "name": "tsihkodiives",
      "score": 31.0,
      "roi_score": 0.0,
      "calibration_score": 50.0,
      "consistency_score": 50.0,
      "early_entry_score": 0.0,
      "volume_score": 85.1,
      "roi": -52.3,
      "cash_pnl": -308180.42,
      "realized_pnl": 29882.94,
      "total_usdc": 70550.29,
      "trade_count": 500,
      "market_count": 14,
      "position_count": 500,
      "resolved_count": 0,
      "win_rate": 0,
      "z_score": 0.0,
      "last_active": "2026-07-01T23:34:25+00:00",
      "top_markets": [
        "Will Paraguay win the 2026 FIFA World Cup?",
        "Will Croatia win the 2026 FIFA World Cup?",
        "Will Norway win the 2026 FIFA World Cup?"
      ],
      "signals": [
        {
          "market": "Will Switzerland win the 2026 FIFA World Cup?",
          "signal": "ENTER",
          "avg_price": 0.0074,
          "cur_price": 0.0075,
          "usdc_size": 17269.66,
          "outcome": "Yes"
        },
        {
          "market": "Will Brazil win the 2026 FIFA World Cup?",
          "signal": "ENTER",
          "avg_price": 0.0628,
          "cur_price": 0.0645,
          "usdc_size": 35221.82,
          "outcome": "Yes"
        },
        {
          "market": "Will Algeria win the 2026 FIFA World Cup?",
          "signal": "LATE",
          "avg_price": 0.001,
          "cur_price": 0.0005,
          "usdc_size": 1576.91,
          "outcome": "Yes"
        },
        {
          "market": "Will Ghana win the 2026 FIFA World Cup?",
          "signal": "LATE",
          "avg_price": 0.001,
          "cur_price": 0.0005,
          "usdc_size": 1364.76,
          "outcome": "Yes"
        },
        {
          "market": "Will Paraguay win the 2026 FIFA World Cup?",
          "signal": "LATE",
          "avg_price": 0.001,
          "cur_price": 0.0015,
          "usdc_size": 2547.69,
          "outcome": "Yes"
        },
        {
          "market": "Will Australia win the 2026 FIFA World Cup?",
          "signal": "SKIP",
          "avg_price": 0.0026,
          "cur_price": 0.0015,
          "usdc_size": 2250.0,
          "outcome": "Yes"
        },
        {
          "market": "Will Morocco win the 2026 FIFA World Cup?",
          "signal": "SKIP",
          "avg_price": 0.0144,
          "cur_price": 0.0255,
          "usdc_size": 24901.44,
          "outcome": "Yes"
        },
        {
          "market": "Will Belgium win the 2026 FIFA World Cup?",
          "signal": "SKIP",
          "avg_price": 0.0124,
          "cur_price": 0.0155,
          "usdc_size": 14531.84,
          "outcome": "Yes"
        },
        {
          "market": "Will England win the 2026 FIFA World Cup?",
          "signal": "SKIP",
          "avg_price": 0.0757,
          "cur_price": 0.0825,
          "usdc_size": 24775.04,
          "outcome": "Yes"
        },
        {
          "market": "Will Spain win the 2026 FIFA World Cup?",
          "signal": "SKIP",
          "avg_price": 0.1275,
          "cur_price": 0.1005,
          "usdc_size": 9529.09,
          "outcome": "Yes"
        },
        {
          "market": "Will Argentina win the 2026 FIFA World Cup?",
          "signal": "SKIP",
          "avg_price": 0.879,
          "cur_price": 0.1805,
          "usdc_size": 2358.89,
          "outcome": "No"
        }
      ]
    },
    {
      "wallet": "0x89f967233e8473a0b7f2004b9d1b31ebebd9b9c5",
      "name": "Aristoteles67",
      "score": 30.9,
      "roi_score": 0.0,
      "calibration_score": 50.0,
      "consistency_score": 50.0,
      "early_entry_score": 0.0,
      "volume_score": 83.6,
      "roi": -92.7,
      "cash_pnl": -13892.46,
      "realized_pnl": 796.61,
      "total_usdc": 58430.4,
      "trade_count": 474,
      "market_count": 90,
      "position_count": 45,
      "resolved_count": 0,
      "win_rate": 0,
      "z_score": 0.0,
      "last_active": "2026-07-02T00:38:46+00:00",
      "top_markets": [
        "Will Belgium win on 2026-07-01?",
        "Rio Ave FC vs. Gil Vicente FC: O/U 1.5",
        "SC Braga vs. Estoril Praia: O/U 2.5"
      ],
      "signals": [
        {
          "market": "Will Belgium win the 2026 FIFA World Cup?",
          "signal": "SKIP",
          "avg_price": 0.0142,
          "cur_price": 0.0155,
          "usdc_size": 1089.95,
          "outcome": "Yes"
        }
      ]
    },
    {
      "wallet": "0x575a227b3d9369b06a4aeffb3ab820b407f3bba6",
      "name": "qqq89",
      "score": 30.6,
      "roi_score": 0.0,
      "calibration_score": 50.0,
      "consistency_score": 50.0,
      "early_entry_score": 0.0,
      "volume_score": 81.5,
      "roi": -91.9,
      "cash_pnl": -228085.61,
      "realized_pnl": 38591.51,
      "total_usdc": 44099.84,
      "trade_count": 500,
      "market_count": 12,
      "position_count": 62,
      "resolved_count": 0,
      "win_rate": 0,
      "z_score": 0.0,
      "last_active": "2026-07-02T01:44:26+00:00",
      "top_markets": [
        "Will Ecuador win the 2026 FIFA World Cup?",
        "Will Japan win the 2026 FIFA World Cup?",
        "Will Ivory Coast win the 2026 FIFA World Cup?"
      ],
      "signals": [
        {
          "market": "Will Morocco win the 2026 FIFA World Cup?",
          "signal": "ENTER",
          "avg_price": 0.0248,
          "cur_price": 0.0255,
          "usdc_size": 6489.36,
          "outcome": "Yes"
        },
        {
          "market": "Will Belgium win the 2026 FIFA World Cup?",
          "signal": "LATE",
          "avg_price": 0.016,
          "cur_price": 0.0155,
          "usdc_size": 2575.89,
          "outcome": "Yes"
        }
      ]
    },
    {
      "wallet": "0x8ae0105b2af0c65a6f8024679ca742cad283b4ce",
      "name": "jlo12345",
      "score": 30.6,
      "roi_score": 1.9,
      "calibration_score": 50.0,
      "consistency_score": 50.0,
      "early_entry_score": 0.0,
      "volume_score": 75.3,
      "roi": -47.2,
      "cash_pnl": -6590.34,
      "realized_pnl": 839.37,
      "total_usdc": 19498.75,
      "trade_count": 500,
      "market_count": 10,
      "position_count": 15,
      "resolved_count": 0,
      "win_rate": 0,
      "z_score": 0.0,
      "last_active": "2026-07-02T10:02:02+00:00",
      "top_markets": [
        "Will Senegal win the 2026 FIFA World Cup?",
        "Will Harry Kane be the top goalscorer at the 2026 FIFA World Cup?",
        "Will Belgium win the 2026 FIFA World Cup?"
      ],
      "signals": [
        {
          "market": "Will Spain win the 2026 FIFA World Cup?",
          "signal": "ENTER",
          "avg_price": 0.099,
          "cur_price": 0.1005,
          "usdc_size": 2010.0,
          "outcome": "Yes"
        },
        {
          "market": "Will Belgium win the 2026 FIFA World Cup?",
          "signal": "SKIP",
          "avg_price": 0.011,
          "cur_price": 0.0155,
          "usdc_size": 3616.67,
          "outcome": "Yes"
        },
        {
          "market": "Will Switzerland win the 2026 FIFA World Cup?",
          "signal": "SKIP",
          "avg_price": 0.009,
          "cur_price": 0.0075,
          "usdc_size": 727.5,
          "outcome": "Yes"
        }
      ]
    },
    {
      "wallet": "0x41c7f7d1fb5ce740e010f510f8647c2d238fc8fb",
      "name": "AcapGG",
      "score": 30.2,
      "roi_score": 0.0,
      "calibration_score": 50.0,
      "consistency_score": 50.0,
      "early_entry_score": 0.0,
      "volume_score": 76.9,
      "roi": -100.0,
      "cash_pnl": -32.41,
      "realized_pnl": 0.0,
      "total_usdc": 24154.66,
      "trade_count": 500,
      "market_count": 219,
      "position_count": 2,
      "resolved_count": 0,
      "win_rate": 0,
      "z_score": 0.0,
      "last_active": "2026-07-02T01:43:14+00:00",
      "top_markets": [
        "Counter-Strike: EYEBALLERS vs Omega (BO3) - CCT Europe Series #20 Playoffs",
        "Counter-Strike: BIG vs Bebop (BO3) - CCT Europe Series #20 Playoffs",
        "Counter-Strike: RED Canids vs Spirit (BO3) - IEM Rio Group A"
      ],
      "signals": []
    },
    {
      "wallet": "0x482bf5accdecfaffa67c14d4d4fbb59f428a3266",
      "name": "Winry",
      "score": 30.1,
      "roi_score": 0.0,
      "calibration_score": 50.0,
      "consistency_score": 50.0,
      "early_entry_score": 0.0,
      "volume_score": 76.2,
      "roi": -55.6,
      "cash_pnl": -18716.88,
      "realized_pnl": 10485.59,
      "total_usdc": 22073.42,
      "trade_count": 500,
      "market_count": 8,
      "position_count": 162,
      "resolved_count": 0,
      "win_rate": 0,
      "z_score": 0.0,
      "last_active": "2026-07-02T11:04:47+00:00",
      "top_markets": [
        "Will USA win the 2026 FIFA World Cup?",
        "Will Norway win the 2026 FIFA World Cup?",
        "Will Mexico win the 2026 FIFA World Cup?"
      ],
      "signals": [
        {
          "market": "Will USA win the 2026 FIFA World Cup?",
          "signal": "ENTER",
          "avg_price": 0.0267,
          "cur_price": 0.0275,
          "usdc_size": 9966.94,
          "outcome": "Yes"
        },
        {
          "market": "Will Belgium win the 2026 FIFA World Cup?",
          "signal": "LATE",
          "avg_price": 0.0149,
          "cur_price": 0.0155,
          "usdc_size": 1033.32,
          "outcome": "Yes"
        },
        {
          "market": "Will Mexico win the 2026 FIFA World Cup?",
          "signal": "LATE",
          "avg_price": 0.0356,
          "cur_price": 0.0345,
          "usdc_size": 2090.79,
          "outcome": "Yes"
        }
      ]
    },
    {
      "wallet": "0x37ee3bceb4fbf028fb90d1463a4a5354da02f86f",
      "name": "0x37ee3BCEb4fBf028fb90D1463A4a5354Da02f86F-1781205947489",
      "score": 30.0,
      "roi_score": 0.0,
      "calibration_score": 50.0,
      "consistency_score": 50.0,
      "early_entry_score": 0.0,
      "volume_score": 75.4,
      "roi": -95.9,
      "cash_pnl": -1350299.36,
      "realized_pnl": -87144.19,
      "total_usdc": 19712.8,
      "trade_count": 500,
      "market_count": 18,
      "position_count": 47,
      "resolved_count": 0,
      "win_rate": 0,
      "z_score": 0.0,
      "last_active": "2026-07-02T11:07:08+00:00",
      "top_markets": [
        "Will Switzerland win the 2026 FIFA World Cup?",
        "Will France win the 2026 FIFA World Cup?",
        "Will Portugal win the 2026 FIFA World Cup?"
      ],
      "signals": [
        {
          "market": "Will Belgium win the 2026 FIFA World Cup?",
          "signal": "LATE",
          "avg_price": 0.0166,
          "cur_price": 0.0155,
          "usdc_size": 2553.53,
          "outcome": "Yes"
        },
        {
          "market": "Will Australia win the 2026 FIFA World Cup?",
          "signal": "SKIP",
          "avg_price": 0.0166,
          "cur_price": 0.0015,
          "usdc_size": 4286.36,
          "outcome": "Yes"
        },
        {
          "market": "Will Paraguay win the 2026 FIFA World Cup?",
          "signal": "SKIP",
          "avg_price": 0.0166,
          "cur_price": 0.0015,
          "usdc_size": 1071.27,
          "outcome": "Yes"
        },
        {
          "market": "Will Switzerland win the 2026 FIFA World Cup?",
          "signal": "SKIP",
          "avg_price": 0.0166,
          "cur_price": 0.0075,
          "usdc_size": 5139.93,
          "outcome": "Yes"
        },
        {
          "market": "Will Croatia win the 2026 FIFA World Cup?",
          "signal": "SKIP",
          "avg_price": 0.0166,
          "cur_price": 0.0035,
          "usdc_size": 1249.44,
          "outcome": "Yes"
        },
        {
          "market": "Will Brazil win the 2026 FIFA World Cup?",
          "signal": "SKIP",
          "avg_price": 0.0166,
          "cur_price": 0.0645,
          "usdc_size": 3858.14,
          "outcome": "Yes"
        },
        {
          "market": "Will Mexico win the 2026 FIFA World Cup?",
          "signal": "SKIP",
          "avg_price": 0.0166,
          "cur_price": 0.0345,
          "usdc_size": 2063.65,
          "outcome": "Yes"
        },
        {
          "market": "Will USA win the 2026 FIFA World Cup?",
          "signal": "SKIP",
          "avg_price": 0.0166,
          "cur_price": 0.0275,
          "usdc_size": 1644.94,
          "outcome": "Yes"
        },
        {
          "market": "Will England win the 2026 FIFA World Cup?",
          "signal": "SKIP",
          "avg_price": 0.0166,
          "cur_price": 0.0825,
          "usdc_size": 4934.82,
          "outcome": "Yes"
        },
        {
          "market": "Will Morocco win the 2026 FIFA World Cup?",
          "signal": "SKIP",
          "avg_price": 0.0166,
          "cur_price": 0.0255,
          "usdc_size": 1519.33,
          "outcome": "Yes"
        },
        {
          "market": "Will Argentina win the 2026 FIFA World Cup?",
          "signal": "SKIP",
          "avg_price": 0.0166,
          "cur_price": 0.1805,
          "usdc_size": 9441.23,
          "outcome": "Yes"
        },
        {
          "market": "Will France win the 2026 FIFA World Cup?",
          "signal": "SKIP",
          "avg_price": 0.5,
          "cur_price": 0.3505,
          "usdc_size": 10271.28,
          "outcome": "Yes"
        },
        {
          "market": "Will Portugal win the 2026 FIFA World Cup?",
          "signal": "SKIP",
          "avg_price": 0.0166,
          "cur_price": 0.0605,
          "usdc_size": 1396.81,
          "outcome": "Yes"
        }
      ]
    },
    {
      "wallet": "0xfa0b22c9ccd486972f4d9f959fa77394ad419672",
      "name": "noobslayer44444",
      "score": 30.0,
      "roi_score": 0.0,
      "calibration_score": 50.0,
      "consistency_score": 50.0,
      "early_entry_score": 0.0,
      "volume_score": 75.0,
      "roi": -99.4,
      "cash_pnl": -135600.39,
      "realized_pnl": 1880.5,
      "total_usdc": 18926.35,
      "trade_count": 500,
      "market_count": 40,
      "position_count": 304,
      "resolved_count": 0,
      "win_rate": 0,
      "z_score": 0.0,
      "last_active": "2026-07-01T17:24:31+00:00",
      "top_markets": [
        "Will the Cleveland Cavaliers win the 2026 NBA Finals?",
        "Counter-Strike: FaZe vs Vitality (BO3) - IEM Atlanta Group A",
        "LoL: BNK FEARX vs T1 (BO3) - Esports World Cup Korea Qualifier Playoffs"
      ],
      "signals": [
        {
          "market": "Will Belgium win the 2026 FIFA World Cup?",
          "signal": "SKIP",
          "avg_price": 0.013,
          "cur_price": 0.0155,
          "usdc_size": 775.0,
          "outcome": "Yes"
        }
      ]
    },
    {
      "wallet": "0x01be84df4f1c88e78dc67234e7862d96aacc543b",
      "name": "123456123456123456",
      "score": 29.9,
      "roi_score": 4.0,
      "calibration_score": 50.0,
      "consistency_score": 50.0,
      "early_entry_score": 0.0,
      "volume_score": 61.8,
      "roi": -43.9,
      "cash_pnl": -799.58,
      "realized_pnl": 0.0,
      "total_usdc": 3327.53,
      "trade_count": 40,
      "market_count": 33,
      "position_count": 22,
      "resolved_count": 0,
      "win_rate": 0,
      "z_score": 0.0,
      "last_active": "2026-07-02T01:32:29+00:00",
      "top_markets": [
        "Will JD Vance win the 2028 US Presidential Election?",
        "Will J.D. Vance win the 2028 Republican presidential nomination?",
        "Will Belgium win the 2026 FIFA World Cup?"
      ],
      "signals": [
        {
          "market": "Will Belgium win the 2026 FIFA World Cup?",
          "signal": "LATE",
          "avg_price": 0.0149,
          "cur_price": 0.0155,
          "usdc_size": 569.93,
          "outcome": "Yes"
        }
      ]
    },
    {
      "wallet": "0x0b575d1c96dfd3f20a322329a18bb07551e071d6",
      "name": "0x0b575d1c96dfd3F20a322329a18BB07551E071D6-1769810714094",
      "score": 29.8,
      "roi_score": 0.0,
      "calibration_score": 50.0,
      "consistency_score": 50.0,
      "early_entry_score": 0.0,
      "volume_score": 73.0,
      "roi": -98.9,
      "cash_pnl": -23421.14,
      "realized_pnl": -66.24,
      "total_usdc": 14492.88,
      "trade_count": 500,
      "market_count": 173,
      "position_count": 368,
      "resolved_count": 0,
      "win_rate": 0,
      "z_score": 0.0,
      "last_active": "2026-07-02T03:10:10+00:00",
      "top_markets": [
        "Ethereum Up or Down - March 25, 8:15PM-8:20PM ET",
        "Solana Up or Down - March 29, 4:35PM-4:40PM ET",
        "Ethereum Up or Down - March 29, 8:55AM-9:00AM ET"
      ],
      "signals": []
    },
    {
      "wallet": "0x19b74eacfc57da8b496d9e309b8b74e296769ee6",
      "name": "noob4dezenuts",
      "score": 29.6,
      "roi_score": 0.0,
      "calibration_score": 50.0,
      "consistency_score": 50.0,
      "early_entry_score": 0.0,
      "volume_score": 71.5,
      "roi": -96.1,
      "cash_pnl": -25290.92,
      "realized_pnl": -211.15,
      "total_usdc": 11869.62,
      "trade_count": 500,
      "market_count": 155,
      "position_count": 500,
      "resolved_count": 0,
      "win_rate": 0,
      "z_score": 0.0,
      "last_active": "2026-07-02T10:49:22+00:00",
      "top_markets": [
        "Will Ji\u0159\u00ed Lehe\u010dka be the 2026 Men\u2019s Wimbledon winner?",
        "Will Oklahoma City Thunder win the 2027 NBA Finals?",
        "Will San Antonio Spurs win the 2027 NBA Finals?"
      ],
      "signals": []
    },
    {
      "wallet": "0xbddf61af533ff524d27154e589d2d7a81510c684",
      "name": "Countryside",
      "score": 28.2,
      "roi_score": 0.0,
      "calibration_score": 50.0,
      "consistency_score": 50.0,
      "early_entry_score": 0.0,
      "volume_score": 57.1,
      "roi": -99.1,
      "cash_pnl": -36296301.84,
      "realized_pnl": 30210.65,
      "total_usdc": 1791.73,
      "trade_count": 500,
      "market_count": 4,
      "position_count": 500,
      "resolved_count": 0,
      "win_rate": 0,
      "z_score": 0.0,
      "last_active": "2026-07-02T10:39:34+00:00",
      "top_markets": [
        "Will Sweden win the 2026 FIFA World Cup?",
        "Will Ghana win the 2026 FIFA World Cup?"
      ],
      "signals": [
        {
          "market": "Will Algeria win the 2026 FIFA World Cup?",
          "signal": "LATE",
          "avg_price": 0.001,
          "cur_price": 0.0005,
          "usdc_size": 2335.26,
          "outcome": "Yes"
        },
        {
          "market": "Will Belgium win the 2026 FIFA World Cup?",
          "signal": "LATE",
          "avg_price": 0.015,
          "cur_price": 0.0155,
          "usdc_size": 41711.89,
          "outcome": "Yes"
        },
        {
          "market": "Will Brazil win the 2026 FIFA World Cup?",
          "signal": "SKIP",
          "avg_price": 0.048,
          "cur_price": 0.0645,
          "usdc_size": 83520.71,
          "outcome": "Yes"
        },
        {
          "market": "Will England win the 2026 FIFA World Cup?",
          "signal": "SKIP",
          "avg_price": 0.0736,
          "cur_price": 0.0825,
          "usdc_size": 106203.34,
          "outcome": "Yes"
        },
        {
          "market": "Will Norway win the 2026 FIFA World Cup?",
          "signal": "SKIP",
          "avg_price": 0.0219,
          "cur_price": 0.0195,
          "usdc_size": 3090.34,
          "outcome": "Yes"
        }
      ]
    }
  ],
  "markets": [
    {
      "id": "0x32cfa52198e85e070d1b17d1b53c5c3a6aaae7736cdc33fa6aa04d353f0c2811",
      "question": "Will Belgium win the 2026 FIFA World Cup?",
      "volume": "96294083.02189325",
      "liquidity": "4117053.07115",
      "end_date": "2026-07-20T00:00:00Z"
    },
    {
      "id": "0x881a3ffa618b6ae0ab95a5637e310afb1afc2d99c921bfe3235b15eccfce0344",
      "question": "Will Ghana win the 2026 FIFA World Cup?",
      "volume": "85879047.65381382",
      "liquidity": "14659515.11022",
      "end_date": "2026-07-20T00:00:00Z"
    },
    {
      "id": "0x7b52405ad0e0d31bfe970940b67d77f24ecedeab8a2361c11148c02a006e325c",
      "question": "Will Norway win the 2026 FIFA World Cup?",
      "volume": "90425443.73682971",
      "liquidity": "2385481.05115",
      "end_date": "2026-07-20T00:00:00Z"
    },
    {
      "id": "0x5ccfe1b69a582d2985db08a8481a0d74c314b1fce9b4711ae2efb2c6467fe6aa",
      "question": "Will Mexico win the 2026 FIFA World Cup?",
      "volume": "119092714.91014124",
      "liquidity": "1007724.4607",
      "end_date": "2026-07-20T00:00:00Z"
    },
    {
      "id": "0xcdb1f0400949238a63d3e88243d2ada08cd9c2a71985ced9f0cfd5e66354cf90",
      "question": "Will USA win the 2026 FIFA World Cup?",
      "volume": "122027684.95738168",
      "liquidity": "3118584.50152",
      "end_date": "2026-07-20T00:00:00Z"
    },
    {
      "id": "0x375409bc5eeeff961e82b479caeccc20f33d15738e5bce1186d628aa3d9dfb1f",
      "question": "Will England win the 2026 FIFA World Cup?",
      "volume": "71600012.03227752",
      "liquidity": "5323750.45322",
      "end_date": "2026-07-20T00:00:00Z"
    },
    {
      "id": "0xf426c69674c6637f2b458c76d9920faa814d4daa8c308e0b8ba554dda509cb8b",
      "question": "Will Shimelis Abdisa be the next Prime Minister of Ethiopia?",
      "volume": "28173650.541130003",
      "liquidity": "27728.23959",
      "end_date": "2026-06-01T00:00:00Z"
    },
    {
      "id": "0x37a6de1b21803e5f3fb1965116218215d79963af4f7e51659696366267a63a03",
      "question": "Will Morocco win the 2026 FIFA World Cup?",
      "volume": "112272078.37896156",
      "liquidity": "2201105.40696",
      "end_date": "2026-07-20T00:00:00Z"
    },
    {
      "id": "0xe5bd80313b8859e3f5761568ac9498866ea9d4419e4d1b6a877a9a9bd2754cb4",
      "question": "Will Croatia win the 2026 FIFA World Cup?",
      "volume": "101604219.76143342",
      "liquidity": "4795864.80605",
      "end_date": "2026-07-20T00:00:00Z"
    },
    {
      "id": "0x9b6fef249040fd17e9c107955b37ac2c3e923509b6b0ff01cc463a331ddeb894",
      "question": "Will France win the 2026 FIFA World Cup?",
      "volume": "88058078.36230418",
      "liquidity": "8262470.906",
      "end_date": "2026-07-20T00:00:00Z"
    },
    {
      "id": "0x098e2be3df8ab529940c567819f8ef007cf007820e9d627642a5bbfaa42af372",
      "question": "Will Australia win the 2026 FIFA World Cup?",
      "volume": "82351982.82911621",
      "liquidity": "12686258.8653",
      "end_date": "2026-07-20T00:00:00Z"
    },
    {
      "id": "0x4f3421fb2daf5cca7430ed8d8132463963081572d75434393a1808fdb8829fe8",
      "question": "Will Portugal win the 2026 FIFA World Cup?",
      "volume": "88384885.40512139",
      "liquidity": "3755517.08974",
      "end_date": "2026-07-20T00:00:00Z"
    },
    {
      "id": "0x3bc69cb672591e4fcd2ef856b64b219a906e15d4601b50066ac81a446574dfaf",
      "question": "Will Cape Verde win the 2026 FIFA World Cup?",
      "volume": "94781144.84490292",
      "liquidity": "9297297.33327",
      "end_date": "2026-07-20T00:00:00Z"
    },
    {
      "id": "0x30d55d8124ee1e12dabe89201badc45669b81dff69e4ce44d961f32878ec178a",
      "question": "Will Brazil win the 2026 FIFA World Cup?",
      "volume": "72731399.87648626",
      "liquidity": "4724835.63049",
      "end_date": "2026-07-20T00:00:00Z"
    },
    {
      "id": "0x3a26ca6425e2d98f14935670bc22cdb0744defc6f6d83c65f8c413a921c5c70c",
      "question": "Will Switzerland win the 2026 FIFA World Cup?",
      "volume": "81581068.79754739",
      "liquidity": "6624460.8692",
      "end_date": "2026-07-20T00:00:00Z"
    },
    {
      "id": "0x5a59d269c2b5108cd2f64c624e46ee2c8b5cfd88b882582565f927918315b6aa",
      "question": "Will Algeria win the 2026 FIFA World Cup?",
      "volume": "88012177.80721623",
      "liquidity": "10646367.62482",
      "end_date": "2026-07-20T00:00:00Z"
    },
    {
      "id": "0xed2b27cf6f1dc265a4889b2b68be11b8cf85c40de0d755e1b88fd3299cc542a4",
      "question": "Will Vladimir Putin be the next leader out before 2027?",
      "volume": "2539909.6429830017",
      "liquidity": "83942.5887",
      "end_date": "2026-12-31T00:00:00Z"
    },
    {
      "id": "0x0c4cd2055d6ea89354ffddc55d6dbcef9355748112ea952fc925f3db6a5c457f",
      "question": "Will Argentina win the 2026 FIFA World Cup?",
      "volume": "90101371.17657965",
      "liquidity": "9519476.17435",
      "end_date": "2026-07-20T00:00:00Z"
    },
    {
      "id": "0x675bba4df50fd123f7fbfbafa67e9b75f4092d85ce0f9148ce78fc945964c856",
      "question": "Will Paraguay win the 2026 FIFA World Cup?",
      "volume": "95573235.48286405",
      "liquidity": "15567861.45105",
      "end_date": "2026-07-20T00:00:00Z"
    },
    {
      "id": "0x7976b8dbacf9077eb1453a62bcefd6ab2df199acd28aad276ff0d920d6992892",
      "question": "Will Spain win the 2026 FIFA World Cup?",
      "volume": "75795993.04794508",
      "liquidity": "8240417.13602",
      "end_date": "2026-07-20T00:00:00Z"
    }
  ],
  "consensus": [
    {
      "market": "Will Brazil win the 2026 FIFA World Cup?",
      "side": "Yes",
      "whales": 5,
      "avg_entry": 0.0648,
      "capital": 48081.79,
      "wallets": [
        "0x24c8cf69a0e0a17eee21f69d29752bfa32e823e1",
        "0x6a678ca367432d28cb6aa55bb6bc57d8f53bdf6f",
        "0xb3cfe7615d64db8dfa743a1b1a2b976911460ebd",
        "0xb22598b366c9ec16a3e97dc90e09dd5fd8dc3d54",
        "0x6db983ff1cbc85249e64e6ccd101aaa613ba4ab5"
      ]
    },
    {
      "market": "Will Spain win the 2026 FIFA World Cup?",
      "side": "Yes",
      "whales": 2,
      "avg_entry": 0.0995,
      "capital": 2903.24,
      "wallets": [
        "0x14c32680ffc318892e0d019181e4161aa34cdf68",
        "0x8ae0105b2af0c65a6f8024679ca742cad283b4ce"
      ]
    }
  ]
}